Workbook

Sheet Repo rate
A1: RBI Repo rate
A4: 23-06-2026 | B4: 5.25

Sheet Punjab National Bank
A1: Bank | B1: Punjab National Bank
A2: Interest rate link | B2: https://pnb.bank.in/Retail-Advances-interst-rate-on-advances-linked-to-mclr.html
A3: Credit score range given | B3: Yes
A4: Interest rates as per score | B4: Yes
A5: Gender split | B5: No
A6: Occupation split | B6: No
A7: Rate types | B7: Floating & Fixed
A8: Rate base | B8: Repo + Mark-up + BSP
A9: Special Govt. Employees | B9: Yes
A10: Loan Type - Term Loan | B10: Yes
A11: Loan Type - Overdraft | B11: Yes
A12: Top up | B12: Yes
A13: Rate varies by insurance | B13: No
A14: Updated as on | B14: 46249
A15: Rate | B15: Floating rate | H15: Fixed Rate
B16: RLLR | D16: BSP | E16: RLLR + BSP | G16: ROI
B17: Repo Rate | C17: Markup | D17: Business Strategic Premium | E17: Rate base | F17: Discount / Extra | G17: Final rate | H17: Tenure upto 10 years | I17: Tenure above 10 years
A19: Scheme | B19: Housing Loan For Public
A20: Loan Type | B20: Term Loan
A22: Condition
A23: Loan amount | B23: > 30 lakhs
A25: 800+ | B25: ='Repo rate'!$B$4 -> 5.25 | C25: 2.75 | D25: 0.1 | E25: =B25+C25+D25 -> 8.1 | F25: -0.85 | G25: =E25+F25 -> 7.25 | H25: 8.25 | I25: 8.75 | K25: =I25-G25 -> 1.5
A26: PNB Pride | B26: ='Repo rate'!$B$4 -> 5.25 | C26: 2.75 | D26: 0.1 | E26: =B26+C26+D26 -> 8.1 | F26: -0.8 | G26: =E26+F26 -> 7.3 | H26: 8.3 | I26: 8.8 | K26: =I26-G26 -> 1.5
A27: 750 - 799 | B27: ='Repo rate'!$B$4 -> 5.25 | C27: 2.75 | D27: 0.1 | E27: =B27+C27+D27 -> 8.1 | F27: -0.8 | G27: =E27+F27 -> 7.3 | H27: 8.3 | I27: 8.8 | K27: =I27-G27 -> 1.5
A28: 700 - 749 | B28: ='Repo rate'!$B$4 -> 5.25 | C28: 2.75 | D28: 0.1 | E28: =B28+C28+D28 -> 8.1 | F28: -0.25 | G28: =E28+F28 -> 7.85 | H28: 8.85 | I28: 9.35 | K28: =I28-G28 -> 1.5
A29: 600 - 699 | B29: ='Repo rate'!$B$4 -> 5.25 | C29: 2.75 | D29: 0.1 | E29: =B29+C29+D29 -> 8.1 | F29: 0.95 | G29: =E29+F29 -> 9.05 | H29: 10.05 | I29: 10.55 | K29: =I29-G29 -> 1.5
A31: Condition
A32: Loan amount | B32: < 30 lakhs
A34: PNB Pride | B34: ='Repo rate'!$B$4 -> 5.25 | C34: 2.75 | D34: 0.1 | E34: =B34+C34+D34 -> 8.1 | F34: -0.7 | G34: =E34+F34 -> 7.4 | H34: 8.4 | I34: 8.9 | K34: =I34-G34 -> 1.5
A35: 750+ | B35: ='Repo rate'!$B$4 -> 5.25 | C35: 2.75 | D35: 0.1 | E35: =B35+C35+D35 -> 8.1 | F35: -0.7 | G35: =E35+F35 -> 7.4 | H35: 8.4 | I35: 8.9 | K35: =I35-G35 -> 1.5
A36: 700 - 749 | B36: ='Repo rate'!$B$4 -> 5.25 | C36: 2.75 | D36: 0.1 | E36: =B36+C36+D36 -> 8.1 | F36: -0.15 | G36: =E36+F36 -> 7.95 | H36: 8.95 | I36: 9.45 | K36: =I36-G36 -> 1.5
A37: 600 - 699 | B37: ='Repo rate'!$B$4 -> 5.25 | C37: 2.75 | D37: 0.1 | E37: =B37+C37+D37 -> 8.1 | F37: 1.05 | G37: =E37+F37 -> 9.15 | H37: 10.15 | I37: 10.65 | K37: =I37-G37 -> 1.5
A39: Scheme | B39: PNB Max-Saver
A40: Loan type | B40: Overdraft
A42: Condition
A43: Loan amount | B43: > 30 lakhs
A45: 800+ | B45: ='Repo rate'!$B$4 -> 5.25 | C45: 2.75 | D45: 0.1 | E45: =B45+C45+D45 -> 8.1 | F45: -0.7 | G45: =E45+F45 -> 7.4 | H45: 8.4 | I45: 8.9 | K45: =I45-G45 -> 1.5
A46: PNB Pride | B46: ='Repo rate'!$B$4 -> 5.25 | C46: 2.75 | D46: 0.1 | E46: =B46+C46+D46 -> 8.1 | F46: -0.65 | G46: =E46+F46 -> 7.45 | H46: 8.45 | I46: 8.95 | K46: =I46-G46 -> 1.5
A47: 750 - 799 | B47: ='Repo rate'!$B$4 -> 5.25 | C47: 2.75 | D47: 0.1 | E47: =B47+C47+D47 -> 8.1 | F47: -0.65 | G47: =E47+F47 -> 7.45 | H47: 8.45 | I47: 8.95 | K47: =I47-G47 -> 1.5
A48: 700 - 749 | B48: ='Repo rate'!$B$4 -> 5.25 | C48: 2.75 | D48: 0.1 | E48: =B48+C48+D48 -> 8.1 | F48: -0.1 | G48: =E48+F48 -> 8 | H48: 9 | I48: 9.5 | K48: =I48-G48 -> 1.5
A49: 600 - 699 | B49: ='Repo rate'!$B$4 -> 5.25 | C49: 2.75 | D49: 0.1 | E49: =B49+C49+D49 -> 8.1 | F49: 1.1 | G49: =E49+F49 -> 9.2 | H49: 10.2 | I49: 10.7 | K49: =I49-G49 -> 1.5
A51: Condition
A52: Loan amount | B52: < 30 lakhs
A54: PNB Pride | B54: ='Repo rate'!$B$4 -> 5.25 | C54: 2.75 | D54: 0.1 | E54: =B54+C54+D54 -> 8.1 | F54: -0.55 | G54: =E54+F54 -> 7.55 | H54: 8.55 | I54: 9.05 | K54: =I54-G54 -> 1.5
A55: 750+ | B55: ='Repo rate'!$B$4 -> 5.25 | C55: 2.75 | D55: 0.1 | E55: =B55+C55+D55 -> 8.1 | F55: -0.55 | G55: =E55+F55 -> 7.55 | H55: 8.55 | I55: 9.05 | K55: =I55-G55 -> 1.5
A56: 700 - 749 | B56: ='Repo rate'!$B$4 -> 5.25 | C56: 2.75 | D56: 0.1 | E56: =B56+C56+D56 -> 8.1 | F56: 0 | G56: =E56+F56 -> 8.1 | H56: 9.1 | I56: 9.6 | K56: =I56-G56 -> 1.5
A57: 600 - 699 | B57: ='Repo rate'!$B$4 -> 5.25 | C57: 2.75 | D57: 0.1 | E57: =B57+C57+D57 -> 8.1 | F57: 1.2 | G57: =E57+F57 -> 9.3 | H57: 10.3 | I57: 10.8 | K57: =I57-G57 -> 1.5
K58: =I58-G58 -> 0
A59: Scheme | B59: TOP-UP Loan
A61: Irrespective of Credit score range & Amount limit
A62: Loan type
A63: a. Term Loan | B63: ='Repo rate'!$B$4 -> 5.25 | C63: 2.75 | D63: 0.1 | E63: =B63+C63+D63 -> 8.1 | F63: 0.35 | G63: =E63+F63 -> 8.45 | H63: 9.45 | I63: 9.95 | K63: =I63-G63 -> 1.5
A64: b. Over Draft | B64: ='Repo rate'!$B$4 -> 5.25 | C64: 2.75 | D64: 0.1 | E64: =B64+C64+D64 -> 8.1 | F64: 1.35 | G64: =E64+F64 -> 9.45 | H64: 10.45 | I64: 10.95 | K64: =I64-G64 -> 1.5
A66: Notes for | B66: Housing Loan For Public & PNB Max-Saver
A67: PNB PRIDE - Covers the permanent employees of Central, State Govt. Para Military personnel and Pensioners of Central & State Govt & Employees of PSUs.

Sheet Central Bank of India
A1: Bank | B1: Central Bank of India
A2: Interest rate link | B2: https://centralbank.bank.in/en/retail-scheme-interest
A3: Credit score range given | B3: No
A4: Interest rates as per score | B4: No
A5: Gender split | B5: No
A6: Occupation split | B6: No
A7: Rate types | B7: Floating
A8: Rate base | B8: Repo + Mark-up
A9: Special Govt. Employees | B9: No
A10: Loan Type - Term Loan | B10: Yes
A11: Loan Type - Overdraft | B11: Yes
A12: Rate varies by insurance | B12: No
A13: Updaetd as on | B13: 46217
A14: Rate | B14: Floating rate
B15: RBLR | D15: RBLR | F15: ROI
B16: Repo Rate | C16: Mark-up | D16: Rate base | E16: Discount / Extra | F16: Final rate
A18: Scheme | B18: Cent Home loan
A19: Loan type | B19: Term Loan
A21: 800+ | B21: ='Repo rate'!$B$4 -> 5.25 | C21: 3 | D21: =B21+C21 -> 8.25 | E21: -1.05 | F21: =D21+E21 -> 7.2
A22: 775 - 799 | B22: ='Repo rate'!$B$4 -> 5.25 | C22: 3 | D22: =B22+C22 -> 8.25 | E22: -0.95 | F22: =D22+E22 -> 7.3
A23: 750 - 774 | B23: ='Repo rate'!$B$4 -> 5.25 | C23: 3 | D23: =B23+C23 -> 8.25 | E23: -0.6 | F23: =D23+E23 -> 7.65
A24: 725 - 749 | B24: ='Repo rate'!$B$4 -> 5.25 | C24: 3 | D24: =B24+C24 -> 8.25 | E24: 0.2 | F24: =D24+E24 -> 8.45
A25: 700 - 724 | B25: ='Repo rate'!$B$4 -> 5.25 | C25: 3 | D25: =B25+C25 -> 8.25 | E25: 0.5 | F25: =D25+E25 -> 8.75
A27: Scheme | B27: Cent Home Double Plus Scheme
A28: Loan type | B28: Overdraft
A30: 800+ | B30: ='Repo rate'!$B$4 -> 5.25 | C30: 3 | D30: =B30+C30 -> 8.25 | E30: =0.1 -> 0.1 | F30: =D30+E30 -> 8.35
A31: 775 - 799 | B31: ='Repo rate'!$B$4 -> 5.25 | C31: 3 | D31: =B31+C31 -> 8.25 | E31: 0.2 | F31: =D31+E31 -> 8.45
A32: 750 - 774 | B32: ='Repo rate'!$B$4 -> 5.25 | C32: 3 | D32: =B32+C32 -> 8.25 | E32: 0.3 | F32: =D32+E32 -> 8.55
A33: 725 - 749 | B33: ='Repo rate'!$B$4 -> 5.25 | C33: 3 | D33: =B33+C33 -> 8.25 | E33: 0.5 | F33: =D33+E33 -> 8.75
A34: 700 - 724 | B34: ='Repo rate'!$B$4 -> 5.25 | C34: 3 | D34: =B34+C34 -> 8.25 | E34: =0.9 -> 0.9 | F34: =D34+E34 -> 9.15
A36: Scheme | B36: CENT TOP UP SCHEME
A37: Loan type | B37: Term Loan
A39: 800+ | B39: ='Repo rate'!$B$4 -> 5.25 | C39: 3 | D39: =B39+C39 -> 8.25 | E39: -0.3 | F39: =D39+E39 -> 7.95
A40: 775 - 799 | B40: ='Repo rate'!$B$4 -> 5.25 | C40: 3 | D40: =B40+C40 -> 8.25 | E40: -0.2 | F40: =D40+E40 -> 8.05
A41: 750 - 774 | B41: ='Repo rate'!$B$4 -> 5.25 | C41: 3 | D41: =B41+C41 -> 8.25 | E41: 0.3 | F41: =D41+E41 -> 8.55
A42: 725 - 749 | B42: ='Repo rate'!$B$4 -> 5.25 | C42: 3 | D42: =B42+C42 -> 8.25 | E42: 0.8 | F42: =D42+E42 -> 9.05
A43: 700 - 724 | B43: ='Repo rate'!$B$4 -> 5.25 | C43: 3 | D43: =B43+C43 -> 8.25 | E43: 1.05 | F43: =D43+E43 -> 9.3

Sheet Bank of India
A1: Bank | B1: Bank of India
A2: Interest rate link | B2: https://bankofindia.bank.in/interest-rate/retail-advances
A3: Credit score range given | B3: Yes
A4: Interest rates as per score | B4: Yes
A5: Gender split | B5: No
A6: Occupation split | B6: Yes
A7: Rate types | B7: Floating & Fixed
A8: Rate base | B8: Repo + Mark-up
A9: Special Govt. Employees | B9: Yes
A10: Loan Type - Term Loan | B10: Yes
A11: Loan Type - Overdraft | B11: Yes
A12: Top up | B12: Yes
A13: Rate varies by insurance | B13: Yes
A14: Updaetd as on | B14: 46217
A21: Occupation | B21: Salaried
A22: Rate | D22: Floating rate
B23: RBLR | D23: RBLR | G23: ROI | H23: Remarks
B24: Repo Rate | C24: Markup | D24: Rate base | E24: Credit Risk Premium (CRP) | F24: Business Strategy Discount (BSD) | G24: Final rate
A26: Scheme | B26: Star Home Loan/Star Smart Home Loan/ Star Diamond Home Loan
A27: Loan type | B27: Term loan & Overdraft
A29: 840 + | B29: ='Repo rate'!$B$4 -> 5.25 | C29: 2.85 | D29: =B29+C29 -> 8.1 | E29: 0 | F29: -1 | G29: =D29+E29+F29 -> 7.1
A30: 825 - 839 | B30: ='Repo rate'!$B$4 -> 5.25 | C30: 2.85 | D30: =B30+C30 -> 8.1 | E30: 0 | F30: -0.85 | G30: =D30+E30+F30 -> 7.25
A31: 800 - 824 | B31: ='Repo rate'!$B$4 -> 5.25 | C31: 2.85 | D31: =B31+C31 -> 8.1 | E31: 0 | F31: -0.85 | G31: =D31+E31+F31 -> 7.25
A32: 760 - 799 | B32: ='Repo rate'!$B$4 -> 5.25 | C32: 2.85 | D32: =B32+C32 -> 8.1 | E32: 0 | F32: -0.7 | G32: =D32+E32+F32 -> 7.4
A33: 725 - 759 | B33: ='Repo rate'!$B$4 -> 5.25 | C33: 2.85 | D33: =B33+C33 -> 8.1 | E33: 0.1 | F33: -0.3 | G33: =D33+E33+F33 -> 7.9
A34: 700 - 724 | B34: ='Repo rate'!$B$4 -> 5.25 | C34: 2.85 | D34: =B34+C34 -> 8.1 | E34: 0.3 | F34: 0 | G34: =D34+E34+F34 -> 8.4
A35: <700 | B35: ='Repo rate'!$B$4 -> 5.25 | C35: 2.85 | D35: =B35+C35 -> 8.1 | E35: 1.9 | F35: 0 | G35: =D35+E35+F35 -> 10 | H35: Only for review
A36: -1 & 0 | B36: ='Repo rate'!$B$4 -> 5.25 | C36: 2.85 | D36: =B36+C36 -> 8.1 | E36: 0.3 | F36: -0.5 | G36: =D36+E36+F36 -> 7.9
A38: Scheme | B38: Star Top Up Loan
A39: Loan type | B39: Term loan & Overdraft
A41: 840 + | B41: ='Repo rate'!$B$4 -> 5.25 | C41: 2.85 | D41: =B41+C41 -> 8.1 | E41: 0 | F41: -0.5 | G41: =D41+E41+F41 -> 7.6 | I41: =G41-G29 -> 0.5
A42: 825 - 839 | B42: ='Repo rate'!$B$4 -> 5.25 | C42: 2.85 | D42: =B42+C42 -> 8.1 | E42: 0 | F42: -0.35 | G42: =D42+E42+F42 -> 7.75 | I42: =G42-G30 -> 0.5
A43: 800 - 824 | B43: ='Repo rate'!$B$4 -> 5.25 | C43: 2.85 | D43: =B43+C43 -> 8.1 | E43: 0 | F43: -0.35 | G43: =D43+E43+F43 -> 7.75 | I43: =G43-G31 -> 0.5
A44: 760 - 799 | B44: ='Repo rate'!$B$4 -> 5.25 | C44: 2.85 | D44: =B44+C44 -> 8.1 | E44: 0 | F44: -0.2 | G44: =D44+E44+F44 -> 7.9 | I44: =G44-G32 -> 0.5
A45: 725 - 759 | B45: ='Repo rate'!$B$4 -> 5.25 | C45: 2.85 | D45: =B45+C45 -> 8.1 | E45: 0.1 | F45: 0.2 | G45: =D45+E45+F45 -> 8.4 | I45: =G45-G33 -> 0.5
A46: 700 - 724 | B46: ='Repo rate'!$B$4 -> 5.25 | C46: 2.85 | D46: =B46+C46 -> 8.1 | E46: 0.3 | F46: 0.5 | G46: =D46+E46+F46 -> 8.9 | I46: =G46-G34 -> 0.5
A47: <700 | B47: ='Repo rate'!$B$4 -> 5.25 | C47: 2.85 | D47: =B47+C47 -> 8.1 | E47: 1.9 | F47: 0.5 | G47: =D47+E47+F47 -> 10.5 | H47: Only for review | I47: =G47-G35 -> 0.5
A48: -1 & 0 | B48: ='Repo rate'!$B$4 -> 5.25 | C48: 2.85 | D48: =B48+C48 -> 8.1 | E48: 0.3 | F48: 0 | G48: =D48+E48+F48 -> 8.4 | I48: =G48-G36 -> 0.5
A52: Occupation | B52: Self-Employed
A55: Scheme | B55: Star Home Loan/Star Smart Home Loan/ Star Diamond Home Loan
A56: Loan type | B56: Term loan & Overdraft
A58: 840 + | B58: ='Repo rate'!$B$4 -> 5.25 | C58: 2.85 | D58: =B58+C58 -> 8.1 | E58: 0 | F58: -1 | G58: =D58+E58+F58 -> 7.1
A59: 825 - 839 | B59: ='Repo rate'!$B$4 -> 5.25 | C59: 2.85 | D59: =B59+C59 -> 8.1 | E59: 0 | F59: -0.85 | G59: =D59+E59+F59 -> 7.25
A60: 800 - 824 | B60: ='Repo rate'!$B$4 -> 5.25 | C60: 2.85 | D60: =B60+C60 -> 8.1 | E60: 0 | F60: -0.85 | G60: =D60+E60+F60 -> 7.25
A61: 760 - 799 | B61: ='Repo rate'!$B$4 -> 5.25 | C61: 2.85 | D61: =B61+C61 -> 8.1 | E61: 0 | F61: -0.6 | G61: =D61+E61+F61 -> 7.5
A62: 725 - 759 | B62: ='Repo rate'!$B$4 -> 5.25 | C62: 2.85 | D62: =B62+C62 -> 8.1 | E62: 0.1 | F62: -0.2 | G62: =D62+E62+F62 -> 8
A63: 700 - 724 | B63: ='Repo rate'!$B$4 -> 5.25 | C63: 2.85 | D63: =B63+C63 -> 8.1 | E63: 0.35 | F63: 0 | G63: =D63+E63+F63 -> 8.45
A64: <700 | B64: ='Repo rate'!$B$4 -> 5.25 | C64: 2.85 | D64: =B64+C64 -> 8.1 | E64: 1.9 | F64: 0 | G64: =D64+E64+F64 -> 10 | H64: Only for review
A65: -1 & 0 | B65: ='Repo rate'!$B$4 -> 5.25 | C65: 2.85 | D65: =B65+C65 -> 8.1 | E65: 0.3 | F65: -0.5 | G65: =D65+E65+F65 -> 7.9
A67: Scheme | B67: Star Top Up Loan
A68: Loan type | B68: Term loan & Overdraft
A70: 840 + | B70: ='Repo rate'!$B$4 -> 5.25 | C70: 2.85 | D70: =B70+C70 -> 8.1 | E70: 0 | F70: -0.5 | G70: =D70+E70+F70 -> 7.6
A71: 825 - 839 | B71: ='Repo rate'!$B$4 -> 5.25 | C71: 2.85 | D71: =B71+C71 -> 8.1 | E71: 0 | F71: -0.35 | G71: =D71+E71+F71 -> 7.75
A72: 800 - 824 | B72: ='Repo rate'!$B$4 -> 5.25 | C72: 2.85 | D72: =B72+C72 -> 8.1 | E72: 0 | F72: -0.35 | G72: =D72+E72+F72 -> 7.75
A73: 760 - 799 | B73: ='Repo rate'!$B$4 -> 5.25 | C73: 2.85 | D73: =B73+C73 -> 8.1 | E73: 0 | F73: -0.1 | G73: =D73+E73+F73 -> 8
A74: 725 - 759 | B74: ='Repo rate'!$B$4 -> 5.25 | C74: 2.85 | D74: =B74+C74 -> 8.1 | E74: 0.1 | F74: 0.3 | G74: =D74+E74+F74 -> 8.5
A75: 700 - 724 | B75: ='Repo rate'!$B$4 -> 5.25 | C75: 2.85 | D75: =B75+C75 -> 8.1 | E75: 0.3 | F75: 0.55 | G75: =D75+E75+F75 -> 8.95
A76: <700 | B76: ='Repo rate'!$B$4 -> 5.25 | C76: 2.85 | D76: =B76+C76 -> 8.1 | E76: 1.9 | F76: 0.5 | G76: =D76+E76+F76 -> 10.5 | H76: Only for review
A77: -1 & 0 | B77: ='Repo rate'!$B$4 -> 5.25 | C77: 2.85 | D77: =B77+C77 -> 8.1 | E77: 0.3 | F77: 0 | G77: =D77+E77+F77 -> 8.4
A79: Occupation | B79: Salaried
A81: Scheme | B81: Star Home Loan/Star Smart Home Loan/ Star Diamond Home Loan
A82: Loan type | B82: Term loan & Overdraft
A83: Rate | B83: Fixed | F83: Fixed rate premium
A84: 840 + | B84: ='Repo rate'!$B$4 -> 5.25 | C84: 2.85 | D84: =B84+C84 -> 8.1 | F84: 2.55 | G84: =D84+E84+F84 -> 10.65
A85: 825 - 839 | B85: ='Repo rate'!$B$4 -> 5.25 | C85: 2.85 | D85: =B85+C85 -> 8.1 | F85: 2.55 | G85: =D85+E85+F85 -> 10.65
A86: 800 - 824 | B86: ='Repo rate'!$B$4 -> 5.25 | C86: 2.85 | D86: =B86+C86 -> 8.1 | F86: 2.55 | G86: =D86+E86+F86 -> 10.65
A87: 760 - 799 | B87: ='Repo rate'!$B$4 -> 5.25 | C87: 2.85 | D87: =B87+C87 -> 8.1 | F87: 2.55 | G87: =D87+E87+F87 -> 10.65
A88: 725 - 759 | B88: ='Repo rate'!$B$4 -> 5.25 | C88: 2.85 | D88: =B88+C88 -> 8.1 | F88: 2.65 | G88: =D88+E88+F88 -> 10.75
A89: 700 - 724 | B89: ='Repo rate'!$B$4 -> 5.25 | C89: 2.85 | D89: =B89+C89 -> 8.1 | F89: 2.85 | G89: =D89+E89+F89 -> 10.95
A90: <700 | B90: ='Repo rate'!$B$4 -> 5.25 | C90: 2.85 | D90: =B90+C90 -> 8.1 | F90: 4.45 | G90: =D90+E90+F90 -> 12.55 | H90: Only for review
A91: -1 & 0 | B91: ='Repo rate'!$B$4 -> 5.25 | C91: 2.85 | D91: =B91+C91 -> 8.1 | F91: 2.85 | G91: =D91+E91+F91 -> 10.95
A93: Scheme | B93: Star Top Up Loan
A94: Loan type | B94: Term loan & Overdraft
A96: 840 + | B96: ='Repo rate'!$B$4 -> 5.25 | C96: 2.85 | D96: =B96+C96 -> 8.1 | F96: 3.05 | G96: =D96+E96+F96 -> 11.15
A97: 825 - 839 | B97: ='Repo rate'!$B$4 -> 5.25 | C97: 2.85 | D97: =B97+C97 -> 8.1 | F97: 3.05 | G97: =D97+E97+F97 -> 11.15
A98: 800 - 824 | B98: ='Repo rate'!$B$4 -> 5.25 | C98: 2.85 | D98: =B98+C98 -> 8.1 | F98: 3.05 | G98: =D98+E98+F98 -> 11.15
A99: 760 - 799 | B99: ='Repo rate'!$B$4 -> 5.25 | C99: 2.85 | D99: =B99+C99 -> 8.1 | F99: 3.05 | G99: =D99+E99+F99 -> 11.15
A100: 725 - 759 | B100: ='Repo rate'!$B$4 -> 5.25 | C100: 2.85 | D100: =B100+C100 -> 8.1 | F100: 3.15 | G100: =D100+E100+F100 -> 11.25
A101: 700 - 724 | B101: ='Repo rate'!$B$4 -> 5.25 | C101: 2.85 | D101: =B101+C101 -> 8.1 | F101: 3.35 | G101: =D101+E101+F101 -> 11.45
A102: <700 | B102: ='Repo rate'!$B$4 -> 5.25 | C102: 2.85 | D102: =B102+C102 -> 8.1 | F102: 4.95 | G102: =D102+E102+F102 -> 13.05 | H102: Only for review
A103: -1 & 0 | B103: ='Repo rate'!$B$4 -> 5.25 | C103: 2.85 | D103: =B103+C103 -> 8.1 | F103: 3.35 | G103: =D103+E103+F103 -> 11.45
A105: Occupation | B105: Self-Employed
A107: Scheme | B107: Star Home Loan/Star Smart Home Loan/ Star Diamond Home Loan
A108: Loan type | B108: Term loan & Overdraft
F109: Fixed rate premium
A110: 840 + | B110: ='Repo rate'!$B$4 -> 5.25 | C110: 2.85 | D110: =B110+C110 -> 8.1 | F110: 2.55 | G110: =D110+E110+F110 -> 10.65
A111: 825 - 839 | B111: ='Repo rate'!$B$4 -> 5.25 | C111: 2.85 | D111: =B111+C111 -> 8.1 | F111: 2.55 | G111: =D111+E111+F111 -> 10.65
A112: 800 - 824 | B112: ='Repo rate'!$B$4 -> 5.25 | C112: 2.85 | D112: =B112+C112 -> 8.1 | F112: 2.55 | G112: =D112+E112+F112 -> 10.65
A113: 760 - 799 | B113: ='Repo rate'!$B$4 -> 5.25 | C113: 2.85 | D113: =B113+C113 -> 8.1 | F113: 2.55 | G113: =D113+E113+F113 -> 10.65
A114: 725 - 759 | B114: ='Repo rate'!$B$4 -> 5.25 | C114: 2.85 | D114: =B114+C114 -> 8.1 | F114: 2.65 | G114: =D114+E114+F114 -> 10.75
A115: 700 - 724 | B115: ='Repo rate'!$B$4 -> 5.25 | C115: 2.85 | D115: =B115+C115 -> 8.1 | F115: 2.9 | G115: =D115+E115+F115 -> 11
A116: <700 | B116: ='Repo rate'!$B$4 -> 5.25 | C116: 2.85 | D116: =B116+C116 -> 8.1 | F116: 4.45 | G116: =D116+E116+F116 -> 12.55 | H116: Only for review
A117: -1 & 0 | B117: ='Repo rate'!$B$4 -> 5.25 | C117: 2.85 | D117: =B117+C117 -> 8.1 | F117: 2.85 | G117: =D117+E117+F117 -> 10.95
A119: Scheme | B119: Star Top Up Loan
A120: Loan type | B120: Term loan & Overdraft
A122: 840 + | B122: ='Repo rate'!$B$4 -> 5.25 | C122: 2.85 | D122: =B122+C122 -> 8.1 | F122: 3.05 | G122: =D122+E122+F122 -> 11.15
A123: 825 - 839 | B123: ='Repo rate'!$B$4 -> 5.25 | C123: 2.85 | D123: =B123+C123 -> 8.1 | F123: 3.05 | G123: =D123+E123+F123 -> 11.15
A124: 800 - 824 | B124: ='Repo rate'!$B$4 -> 5.25 | C124: 2.85 | D124: =B124+C124 -> 8.1 | F124: 3.05 | G124: =D124+E124+F124 -> 11.15
A125: 760 - 799 | B125: ='Repo rate'!$B$4 -> 5.25 | C125: 2.85 | D125: =B125+C125 -> 8.1 | F125: 3.05 | G125: =D125+E125+F125 -> 11.15
A126: 725 - 759 | B126: ='Repo rate'!$B$4 -> 5.25 | C126: 2.85 | D126: =B126+C126 -> 8.1 | F126: 3.15 | G126: =D126+E126+F126 -> 11.25
...

Sheet Union Bank of India
A1: Bank | B1: Union Bank of India
A2: Interest rate link | B2: https://www.unionbankofindia.bank.in/en/details/home-loan
A3: Credit score range given | B3: Yes
A4: Interest rates as per score | B4: Yes
A5: Gender split | B5: Yes
A6: Occupation split | B6: Yes
A7: Rate types | B7: Floating & Fixed
A8: Rate base | B8: Repo + Mark-up
A9: Special Govt. Employees | B9: Yes
A10: Loan Type - Term Loan | B10: Yes
A11: Loan Type - Overdraft | B11: Yes
A12: Top up | B12: No
A13: Rate varies by insurance | B13: Yes
A14: Updated as on | B14: 46227
A17: Scheme | B17: UNION HOME
A18: Loan type | B18: Term loan | D18: Floating rate
D19: External Benchmark Lending Rate | G19: Remarks
B20: Repo Rate | C20: Markup | D20: Rate base | E20: Discount | F20: Final rate
A21: Occupation | B21: Salaried
A22: 825+ | B22: ='Repo rate'!$B$4 -> 5.25 | C22: 2.75 | D22: =B22+C22 -> 8 | E22: -0.85 | F22: =D22+E22 -> 7.15
A23: 800 - 824 | B23: ='Repo rate'!$B$4 -> 5.25 | C23: 2.75 | D23: =B23+C23 -> 8 | E23: -0.8 | F23: =D23+E23 -> 7.2
A24: 750 - 799 | B24: ='Repo rate'!$B$4 -> 5.25 | C24: 2.75 | D24: =B24+C24 -> 8 | E24: -0.65 | F24: =D24+E24 -> 7.35
A25: 700 - 749 | B25: ='Repo rate'!$B$4 -> 5.25 | C25: 2.75 | D25: =B25+C25 -> 8 | E25: -0.25 | F25: =D25+E25 -> 7.75 | G25: 0.05 lesser for Female borrower = 7.70
A26: 680 - 699 | B26: ='Repo rate'!$B$4 -> 5.25 | C26: 2.75 | D26: =B26+C26 -> 8 | E26: 0 | F26: =D26+E26 -> 8 | G26: 0.05 lesser for Female borrower = 7.95
A27: 650 - 679 | B27: ='Repo rate'!$B$4 -> 5.25 | C27: 2.75 | D27: =B27+C27 -> 8 | E27: 0.85 | F27: =D27+E27 -> 8.85
A28: 600 - 649 | B28: ='Repo rate'!$B$4 -> 5.25 | C28: 2.75 | D28: =B28+C28 -> 8 | E28: 1.35 | F28: =D28+E28 -> 9.35
A29: -1 & 1 - 5 | B29: ='Repo rate'!$B$4 -> 5.25 | C29: 2.75 | D29: =B29+C29 -> 8 | E29: -0.6 | F29: =D29+E29 -> 7.4
A30: 750+ | B30: ='Repo rate'!$B$4 -> 5.25 | C30: 2.75 | D30: =B30+C30 -> 8 | E30: -0.85 | F30: =D30+E30 -> 7.15 | G30: Government / PSU Employees Only
A32: Occupation | B32: Self-Employed
A33: 825+ | B33: ='Repo rate'!$B$4 -> 5.25 | C33: 2.75 | D33: =B33+C33 -> 8 | E33: -0.85 | F33: =D33+E33 -> 7.15
A34: 800 - 824 | B34: ='Repo rate'!$B$4 -> 5.25 | C34: 2.75 | D34: =B34+C34 -> 8 | E34: -0.8 | F34: =D34+E34 -> 7.2
A35: 750 - 799 | B35: ='Repo rate'!$B$4 -> 5.25 | C35: 2.75 | D35: =B35+C35 -> 8 | E35: -0.6 | F35: =D35+E35 -> 7.4
A36: 700 - 749 | B36: ='Repo rate'!$B$4 -> 5.25 | C36: 2.75 | D36: =B36+C36 -> 8 | E36: -0.15 | F36: =D36+E36 -> 7.85 | G36: 0.05 lesser for Female borrower = 7.80
A37: 680 - 699 | B37: ='Repo rate'!$B$4 -> 5.25 | C37: 2.75 | D37: =B37+C37 -> 8 | E37: 0.1 | F37: =D37+E37 -> 8.1 | G37: 0.05 lesser for Female borrower = 8.05
A38: 650 - 679 | B38: ='Repo rate'!$B$4 -> 5.25 | C38: 2.75 | D38: =B38+C38 -> 8 | E38: 0.85 | F38: =D38+E38 -> 8.85
A39: 600 - 649 | B39: ='Repo rate'!$B$4 -> 5.25 | C39: 2.75 | D39: =B39+C39 -> 8 | E39: 1.35 | F39: =D39+E39 -> 9.35
A40: -1 & 1 - 5 | B40: ='Repo rate'!$B$4 -> 5.25 | C40: 2.75 | D40: =B40+C40 -> 8 | E40: -0.5 | F40: =D40+E40 -> 7.5
A43: Scheme | B43: UNION HOME-SMART SAVE SCHEME
A44: Loan type | B44: Overdraft
A46: Occupation | B46: Salaried
A47: 825+ | B47: ='Repo rate'!$B$4 -> 5.25 | C47: 2.75 | D47: =B47+C47 -> 8 | E47: -0.6 | F47: =D47+E47 -> 7.4
A48: 800 - 824 | B48: ='Repo rate'!$B$4 -> 5.25 | C48: 2.75 | D48: =B48+C48 -> 8 | E48: -0.55 | F48: =D48+E48 -> 7.45
A49: 750 - 799 | B49: ='Repo rate'!$B$4 -> 5.25 | C49: 2.75 | D49: =B49+C49 -> 8 | E49: -0.4 | F49: =D49+E49 -> 7.6
A50: 700 - 749 | B50: ='Repo rate'!$B$4 -> 5.25 | C50: 2.75 | D50: =B50+C50 -> 8 | E50: 0 | F50: =D50+E50 -> 8 | G50: 0.05 lesser for Female borrower = 7.95
A51: 680 - 699 | B51: ='Repo rate'!$B$4 -> 5.25 | C51: 2.75 | D51: =B51+C51 -> 8 | E51: 0.25 | F51: =D51+E51 -> 8.25 | G51: 0.05 lesser for Female borrower = 8.20
A52: 650 - 679 | B52: ='Repo rate'!$B$4 -> 5.25 | C52: 2.75 | D52: =B52+C52 -> 8 | E52: 1.1 | F52: =D52+E52 -> 9.1
A53: 600 - 649 | B53: ='Repo rate'!$B$4 -> 5.25 | C53: 2.75 | D53: =B53+C53 -> 8 | E53: 1.6 | F53: =D53+E53 -> 9.6
A54: -1 & 1 - 5 | B54: ='Repo rate'!$B$4 -> 5.25 | C54: 2.75 | D54: =B54+C54 -> 8 | E54: -0.35 | F54: =D54+E54 -> 7.65
A56: Occupation | B56: Self-Employed
A57: 825+ | B57: ='Repo rate'!$B$4 -> 5.25 | C57: 2.75 | D57: =B57+C57 -> 8 | E57: -0.6 | F57: =D57+E57 -> 7.4
A58: 800 - 824 | B58: ='Repo rate'!$B$4 -> 5.25 | C58: 2.75 | D58: =B58+C58 -> 8 | E58: -0.55 | F58: =D58+E58 -> 7.45
A59: 750 - 799 | B59: ='Repo rate'!$B$4 -> 5.25 | C59: 2.75 | D59: =B59+C59 -> 8 | E59: -0.35 | F59: =D59+E59 -> 7.65
A60: 700 - 749 | B60: ='Repo rate'!$B$4 -> 5.25 | C60: 2.75 | D60: =B60+C60 -> 8 | E60: 0.1 | F60: =D60+E60 -> 8.1 | G60: 0.05 lesser for Female borrower = 8.05
A61: 680 - 699 | B61: ='Repo rate'!$B$4 -> 5.25 | C61: 2.75 | D61: =B61+C61 -> 8 | E61: 0.35 | F61: =D61+E61 -> 8.35 | G61: 0.05 lesser for Female borrower = 8.30
A62: 650 - 679 | B62: ='Repo rate'!$B$4 -> 5.25 | C62: 2.75 | D62: =B62+C62 -> 8 | E62: 1.1 | F62: =D62+E62 -> 9.1
A63: 600 - 649 | B63: ='Repo rate'!$B$4 -> 5.25 | C63: 2.75 | D63: =B63+C63 -> 8 | E63: 1.6 | F63: =D63+E63 -> 9.6
A64: -1 & 1 - 5 | B64: ='Repo rate'!$B$4 -> 5.25 | C64: 2.75 | D64: =B64+C64 -> 8 | E64: -0.25 | F64: =D64+E64 -> 7.75
A66: Notes for | B66: UNION HOME-SMART SAVE SCHEME & UNION HOME
A67: Extra 5 bps concession should be provided in Home Loan to the borrower in case he/she assigns the credit/term/life policy in favour of the Bank
A68: Only Green House scheme - Additional 10 bps lower rate of interest shall be allowed from the date of receipt of required Green- house/ project certificate at Bank/Branch.
A71: Fixed rate
A72: ROI For max 5 years
A73: Credit score range given | B73: No
A74: Gender split | B74: No
A75: Amount | B75: ROI
A76: Up to Rs.30 Lakh | B76: 11.4
A77: Above Rs.30 Lakh to Rs.50.00 Lakh | B77: 12.4
A78: Above Rs.50 Lakh to Rs.200 Lakh | B78: 12.65

Sheet Bank of Baroda
A1: Bank | B1: Bank of Baroda
A2: Interest rate link | B2: https://bankofbaroda.bank.in/loans/home-loan/baroda-home-loan
A3: Credit score range given | B3: No | C3: But from internal executive
A4: Interest rates as per score | B4: No | C4: But from internal executive
A5: Gender split | B5: No
A6: Occupation split | B6: Yes
A7: Rate types | B7: Floating & Fixed
A8: Rate base | B8: Repo + Mark-up
A9: Special Govt. Employees | B9: No
A10: Loan Type - Term Loan | B10: Yes
A11: Loan Type - Overdraft | B11: Yes
A12: Top up | B12: No
A13: Rate varies by insurance | B13: Yes
A14: Updated as on | B14: 46217
A17: Scheme | B17: Baroda Home Loan, Baroda Home Improvement Loan
A18: Loan type | B18: Term loan
D19: Floating rate
D20: Baroda Repo Linked Lending Rate
B21: Repo Rate | C21: Markup | D21: Rate base | E21: Discount | F21: Final rate
A22: Occupation | B22: Salaried & Self-Employed
A23: 825+ | B23: ='Repo rate'!$B$4 -> 5.25 | C23: 2.65 | D23: =B23+C23 -> 7.9 | E23: -0.7 | F23: =D23+E23 -> 7.2
A24: 800 - 824 | B24: ='Repo rate'!$B$4 -> 5.25 | C24: 2.65 | D24: =B24+C24 -> 7.9 | E24: -0.6 | F24: =D24+E24 -> 7.3
A25: 751 - 799 | B25: ='Repo rate'!$B$4 -> 5.25 | C25: 2.65 | D25: =B25+C25 -> 7.9 | E25: -0.5 | F25: =D25+E25 -> 7.4
A26: 726 - 750 | B26: ='Repo rate'!$B$4 -> 5.25 | C26: 2.65 | D26: =B26+C26 -> 7.9 | E26: -0.25 | F26: =D26+E26 -> 7.65
A27: 701 - 725 | B27: ='Repo rate'!$B$4 -> 5.25 | C27: 2.65 | D27: =B27+C27 -> 7.9 | E27: -0.2 | F27: =D27+E27 -> 7.7
A28: 676 - 700 | B28: ='Repo rate'!$B$4 -> 5.25 | C28: 2.65 | D28: =B28+C28 -> 7.9 | E28: 0 | F28: =D28+E28 -> 7.9
A29: 650 - 675 | B29: ='Repo rate'!$B$4 -> 5.25 | C29: 2.65 | D29: =B29+C29 -> 7.9 | E29: 0.4 | F29: =D29+E29 -> 8.3
A30: 625 - 649 | B30: ='Repo rate'!$B$4 -> 5.25 | C30: 2.65 | D30: =B30+C30 -> 7.9 | E30: 0.6 | F30: =D30+E30 -> 8.5
A31: 600 - 624 | B31: ='Repo rate'!$B$4 -> 5.25 | C31: 2.65 | D31: =B31+C31 -> 7.9 | E31: 1.05 | F31: =D31+E31 -> 8.95
A32: -1 | B32: ='Repo rate'!$B$4 -> 5.25 | C32: 2.65 | D32: =B32+C32 -> 7.9 | E32: -0.15 | F32: =D32+E32 -> 7.75
A34: Risk Premium of 0.05% will be levied for customers not obtaining credit insurance cover
A36: Scheme | B36: Baroda Home Loan, Baroda Home Improvement Loan
A37: Loan type | B37: Term loan
A38: Occupation | B38: Salaried
D39: Fixed rate
A40: 825+ | B40: ='Repo rate'!$B$4 -> 5.25 | C40: 2.65 | D40: =B40+C40 -> 7.9 | E40: 1 | F40: =D40+E40 -> 8.9
A41: 800 - 824 | B41: ='Repo rate'!$B$4 -> 5.25 | C41: 2.65 | D41: =B41+C41 -> 7.9 | E41: 1.1 | F41: =D41+E41 -> 9
A42: 751 - 799 | B42: ='Repo rate'!$B$4 -> 5.25 | C42: 2.65 | D42: =B42+C42 -> 7.9 | E42: 1.25 | F42: =D42+E42 -> 9.15
A43: 726 - 750 | B43: ='Repo rate'!$B$4 -> 5.25 | C43: 2.65 | D43: =B43+C43 -> 7.9 | E43: 1.4 | F43: =D43+E43 -> 9.3
A44: 701 - 725 | B44: ='Repo rate'!$B$4 -> 5.25 | C44: 2.65 | D44: =B44+C44 -> 7.9 | E44: 1.5 | F44: =D44+E44 -> 9.4
A45: 676 - 700 | B45: ='Repo rate'!$B$4 -> 5.25 | C45: 2.65 | D45: =B45+C45 -> 7.9 | E45: 1.7 | F45: =D45+E45 -> 9.6
A46: 650 - 675 | B46: ='Repo rate'!$B$4 -> 5.25 | C46: 2.65 | D46: =B46+C46 -> 7.9 | E46: 1.75 | F46: =D46+E46 -> 9.65
A47: 625 - 649 | B47: ='Repo rate'!$B$4 -> 5.25 | C47: 2.65 | D47: =B47+C47 -> 7.9 | E47: 1.9 | F47: =D47+E47 -> 9.8
A48: 600 - 624 | B48: ='Repo rate'!$B$4 -> 5.25 | C48: 2.65 | D48: =B48+C48 -> 7.9 | E48: 2.05 | F48: =D48+E48 -> 9.95
A49: -1 | B49: ='Repo rate'!$B$4 -> 5.25 | C49: 2.65 | D49: =B49+C49 -> 7.9 | E49: -0.15 | F49: =D49+E49 -> 7.75
A51: Occupation | B51: Self - Employed
A52: 825+ | B52: ='Repo rate'!$B$4 -> 5.25 | C52: 2.65 | D52: =B52+C52 -> 7.9 | E52: 1.1 | F52: =D52+E52 -> 9
A53: 800 - 824 | B53: ='Repo rate'!$B$4 -> 5.25 | C53: 2.65 | D53: =B53+C53 -> 7.9 | E53: 1.15 | F53: =D53+E53 -> 9.05
A54: 751 - 799 | B54: ='Repo rate'!$B$4 -> 5.25 | C54: 2.65 | D54: =B54+C54 -> 7.9 | E54: 1.25 | F54: =D54+E54 -> 9.15
A55: 726 - 750 | B55: ='Repo rate'!$B$4 -> 5.25 | C55: 2.65 | D55: =B55+C55 -> 7.9 | E55: 1.35 | F55: =D55+E55 -> 9.25
A56: 701 - 725 | B56: ='Repo rate'!$B$4 -> 5.25 | C56: 2.65 | D56: =B56+C56 -> 7.9 | E56: 1.4 | F56: =D56+E56 -> 9.3
A57: 676 - 700 | B57: ='Repo rate'!$B$4 -> 5.25 | C57: 2.65 | D57: =B57+C57 -> 7.9 | E57: 1.55 | F57: =D57+E57 -> 9.45
A58: 650 - 675 | B58: ='Repo rate'!$B$4 -> 5.25 | C58: 2.65 | D58: =B58+C58 -> 7.9 | E58: 1.65 | F58: =D58+E58 -> 9.55
A59: 625 - 649 | B59: ='Repo rate'!$B$4 -> 5.25 | C59: 2.65 | D59: =B59+C59 -> 7.9 | E59: 1.9 | F59: =D59+E59 -> 9.8
A60: 600 - 624 | B60: ='Repo rate'!$B$4 -> 5.25 | C60: 2.65 | D60: =B60+C60 -> 7.9 | E60: 2.05 | F60: =D60+E60 -> 9.95
A61: -1 | B61: ='Repo rate'!$B$4 -> 5.25 | C61: 2.65 | D61: =B61+C61 -> 7.9 | E61: -0.15 | F61: =D61+E61 -> 7.75
A64: Scheme | B64: Baroda Max Savings Home Loan
A65: Loan type | B65: Overdraft
A66: Occupation | B66: Salaried & Self-Employed
D67: Floating rate
A68: Condition | B68: Loan amount upto Rs. 75 lakhs
A69: 825+ | B69: ='Repo rate'!$B$4 -> 5.25 | C69: 2.65 | D69: =B69+C69 -> 7.9 | E69: -0.7 | F69: =D69+E69 -> 7.2
A70: 800 - 824 | B70: ='Repo rate'!$B$4 -> 5.25 | C70: 2.65 | D70: =B70+C70 -> 7.9 | E70: -0.6 | F70: =D70+E70 -> 7.3
A71: 751 - 799 | B71: ='Repo rate'!$B$4 -> 5.25 | C71: 2.65 | D71: =B71+C71 -> 7.9 | E71: -0.5 | F71: =D71+E71 -> 7.4
A72: 726 - 750 | B72: ='Repo rate'!$B$4 -> 5.25 | C72: 2.65 | D72: =B72+C72 -> 7.9 | E72: -0.25 | F72: =D72+E72 -> 7.65
A73: 701 - 725 | B73: ='Repo rate'!$B$4 -> 5.25 | C73: 2.65 | D73: =B73+C73 -> 7.9 | E73: -0.2 | F73: =D73+E73 -> 7.7
A74: 676 - 700 | B74: ='Repo rate'!$B$4 -> 5.25 | C74: 2.65 | D74: =B74+C74 -> 7.9 | E74: 0 | F74: =D74+E74 -> 7.9
A75: 650 - 675 | B75: ='Repo rate'!$B$4 -> 5.25 | C75: 2.65 | D75: =B75+C75 -> 7.9 | E75: 0.4 | F75: =D75+E75 -> 8.3
A76: 625 - 649 | B76: ='Repo rate'!$B$4 -> 5.25 | C76: 2.65 | D76: =B76+C76 -> 7.9 | E76: 0.6 | F76: =D76+E76 -> 8.5
A77: 600 - 624 | B77: ='Repo rate'!$B$4 -> 5.25 | C77: 2.65 | D77: =B77+C77 -> 7.9 | E77: 1.05 | F77: =D77+E77 -> 8.95
A78: -1 | B78: ='Repo rate'!$B$4 -> 5.25 | C78: 2.65 | D78: =B78+C78 -> 7.9 | E78: -0.15 | F78: =D78+E78 -> 7.75
A80: Condition | B80: Loan amount Above Rs. 75 lakhs
A82: 825+ | B82: ='Repo rate'!$B$4 -> 5.25 | C82: 2.65 | D82: =B82+C82 -> 7.9 | E82: -0.45 | F82: =D82+E82 -> 7.45
A83: 800 - 824 | B83: ='Repo rate'!$B$4 -> 5.25 | C83: 2.65 | D83: =B83+C83 -> 7.9 | E83: -0.35 | F83: =D83+E83 -> 7.55
A84: 751 - 799 | B84: ='Repo rate'!$B$4 -> 5.25 | C84: 2.65 | D84: =B84+C84 -> 7.9 | E84: -0.25 | F84: =D84+E84 -> 7.65
A85: 726 - 750 | B85: ='Repo rate'!$B$4 -> 5.25 | C85: 2.65 | D85: =B85+C85 -> 7.9 | E85: 0 | F85: =D85+E85 -> 7.9
A86: 701 - 725 | B86: ='Repo rate'!$B$4 -> 5.25 | C86: 2.65 | D86: =B86+C86 -> 7.9 | E86: 0.05 | F86: =D86+E86 -> 7.95
A87: 676 - 700 | B87: ='Repo rate'!$B$4 -> 5.25 | C87: 2.65 | D87: =B87+C87 -> 7.9 | E87: 0.25 | F87: =D87+E87 -> 8.15
A88: 650 - 675 | B88: ='Repo rate'!$B$4 -> 5.25 | C88: 2.65 | D88: =B88+C88 -> 7.9 | E88: 0.65 | F88: =D88+E88 -> 8.55
A89: 625 - 649 | B89: ='Repo rate'!$B$4 -> 5.25 | C89: 2.65 | D89: =B89+C89 -> 7.9 | E89: 0.85 | F89: =D89+E89 -> 8.75
A90: 600 - 624 | B90: ='Repo rate'!$B$4 -> 5.25 | C90: 2.65 | D90: =B90+C90 -> 7.9 | E90: 1.3 | F90: =D90+E90 -> 9.2
A91: -1 | B91: ='Repo rate'!$B$4 -> 5.25 | C91: 2.65 | D91: =B91+C91 -> 7.9 | E91: 0.1 | F91: =D91+E91 -> 8
A93: Risk Premium of 0.05% will be levied for customers not obtaining credit insurance cover
A95: Scheme | B95: Baroda Max Savings Home Loan
A96: Loan type | B96: Overdraft
D97: Fixed rate
A98: Condition | B98: Loan amount upto Rs. 75 lakhs
A100: Occupation | B100: Salaried
A101: 825+ | B101: ='Repo rate'!$B$4 -> 5.25 | C101: 2.65 | D101: =B101+C101 -> 7.9 | E101: 1 | F101: =D101+E101 -> 8.9
A102: 800 - 824 | B102: ='Repo rate'!$B$4 -> 5.25 | C102: 2.65 | D102: =B102+C102 -> 7.9 | E102: 1.1 | F102: =D102+E102 -> 9
A103: 751 - 799 | B103: ='Repo rate'!$B$4 -> 5.25 | C103: 2.65 | D103: =B103+C103 -> 7.9 | E103: 1.25 | F103: =D103+E103 -> 9.15
A104: 726 - 750 | B104: ='Repo rate'!$B$4 -> 5.25 | C104: 2.65 | D104: =B104+C104 -> 7.9 | E104: 1.4 | F104: =D104+E104 -> 9.3
A105: 701 - 725 | B105: ='Repo rate'!$B$4 -> 5.25 | C105: 2.65 | D105: =B105+C105 -> 7.9 | E105: 1.5 | F105: =D105+E105 -> 9.4
A106: 676 - 700 | B106: ='Repo rate'!$B$4 -> 5.25 | C106: 2.65 | D106: =B106+C106 -> 7.9 | E106: 1.7 | F106: =D106+E106 -> 9.6
A107: 650 - 675 | B107: ='Repo rate'!$B$4 -> 5.25 | C107: 2.65 | D107: =B107+C107 -> 7.9 | E107: 1.75 | F107: =D107+E107 -> 9.65
A108: 625 - 649 | B108: ='Repo rate'!$B$4 -> 5.25 | C108: 2.65 | D108: =B108+C108 -> 7.9 | E108: 1.9 | F108: =D108+E108 -> 9.8
A109: 600 - 624 | B109: ='Repo rate'!$B$4 -> 5.25 | C109: 2.65 | D109: =B109+C109 -> 7.9 | E109: 2.05 | F109: =D109+E109 -> 9.95
A110: -1 | B110: ='Repo rate'!$B$4 -> 5.25 | C110: 2.65 | D110: =B110+C110 -> 7.9 | E110: -0.15 | F110: =D110+E110 -> 7.75
A112: Occupation | B112: Self-Employed
A113: 825+ | B113: ='Repo rate'!$B$4 -> 5.25 | C113: 2.65 | D113: =B113+C113 -> 7.9 | E113: 1.1 | F113: =D113+E113 -> 9
...

Sheet Canara bank
A1: Bank | B1: Canara bank
A2: Interest rate link | B2: https://www.canarabank.bank.in/pages/rates-of-interest-for-retail-lending-schemes-linked-to-rllr
A3: Credit score range given | B3: Yes | C3: But from internal circular - https://www.scribd.com/document/866685005/Retail-Rate-of-Interest-12042025
A4: Interest rates as per score | B4: Yes
A5: Gender split | B5: Yes
A6: Occupation split | B6: Yes
A7: Rate types | B7: Floating & Fixed
A8: Rate base | B8: Repo + Mark-up
A9: Special Govt. Employees | B9: Yes
A10: Loan Type - Term Loan | B10: Yes
A11: Loan Type - Overdraft | B11: No
A12: Top up | B12: No
A13: Rate varies by insurance | B13: No
A14: Updated as on | B14: 46217
A15: Scheme | B15: HOUSING LOAN
A16: Loan type | B16: Term loan
E18: Floating rate
E19: Repo Linked Lending Rate | H19: ROI
B20: Canara Bank Internal Grouping | C20: Repo Rate | D20: Markup | E20: Rate base | F20: Credit Risk Premium | G20: Discount | H20: Final rate
A21: Condition | B21: Loan amount upto Rs. 50 lakhs
A22: 800+ | B22: CRG-prime | C22: ='Repo rate'!$B$4 -> 5.25 | D22: 2.75 | E22: =C22+D22 -> 8 | F22: 0.05 | G22: -0.75 | H22: =E22+F22+G22 -> 7.3
A23: 750 - 799 | B23: CRG-1 | C23: ='Repo rate'!$B$4 -> 5.25 | D23: 2.75 | E23: =C23+D23 -> 8 | F23: 0.05 | G23: -0.75 | H23: =E23+F23+G23 -> 7.3
A24: 700 - 749 | B24: CRG-2 | C24: ='Repo rate'!$B$4 -> 5.25 | D24: 2.75 | E24: =C24+D24 -> 8 | F24: 0.1 | G24: -0.4 | H24: =E24+F24+G24 -> 7.7
A25: 650 - 699 | B25: CRG-3 | C25: ='Repo rate'!$B$4 -> 5.25 | D25: 2.75 | E25: =C25+D25 -> 8 | F25: 0.5 | G25: 0 | H25: =E25+F25+G25 -> 8.5
A26: < 650 | B26: CRG-4 | C26: ='Repo rate'!$B$4 -> 5.25 | D26: 2.75 | E26: =C26+D26 -> 8 | F26: 2 | G26: 0 | H26: =E26+F26+G26 -> 10
A28: Condition | B28: Loan amount above Rs. 50 lakhs - 100 lakhs
A29: 800+ | B29: CRG-prime | C29: ='Repo rate'!$B$4 -> 5.25 | D29: 2.75 | E29: =C29+D29 -> 8 | F29: 0.05 | G29: -0.8 | H29: =E29+F29+G29 -> 7.25
A30: 750 - 799 | B30: CRG-1 | C30: ='Repo rate'!$B$4 -> 5.25 | D30: 2.75 | E30: =C30+D30 -> 8 | F30: 0.05 | G30: -0.8 | H30: =E30+F30+G30 -> 7.25
A31: 700 - 749 | B31: CRG-2 | C31: ='Repo rate'!$B$4 -> 5.25 | D31: 2.75 | E31: =C31+D31 -> 8 | F31: 0.1 | G31: -0.45 | H31: =E31+F31+G31 -> 7.65
A32: 650 - 699 | B32: CRG-3 | C32: ='Repo rate'!$B$4 -> 5.25 | D32: 2.75 | E32: =C32+D32 -> 8 | F32: 0.5 | G32: 0 | H32: =E32+F32+G32 -> 8.5
A33: < 650 | B33: CRG-4 | C33: ='Repo rate'!$B$4 -> 5.25 | D33: 2.75 | E33: =C33+D33 -> 8 | F33: 2 | G33: -0.1 | H33: =E33+F33+G33 -> 9.9
A35: Condition | B35: Loan amount above Rs. 100 lakhs - 250 lakhs
A36: 800+ | B36: CRG-prime | C36: ='Repo rate'!$B$4 -> 5.25 | D36: 2.75 | E36: =C36+D36 -> 8 | F36: 0.05 | G36: -0.85 | H36: =E36+F36+G36 -> 7.2
A37: 750 - 799 | B37: CRG-1 | C37: ='Repo rate'!$B$4 -> 5.25 | D37: 2.75 | E37: =C37+D37 -> 8 | F37: 0.05 | G37: -0.85 | H37: =E37+F37+G37 -> 7.2
A38: 700 - 749 | B38: CRG-2 | C38: ='Repo rate'!$B$4 -> 5.25 | D38: 2.75 | E38: =C38+D38 -> 8 | F38: 0.1 | G38: -0.5 | H38: =E38+F38+G38 -> 7.6
A39: 650 - 699 | B39: CRG-3 | C39: ='Repo rate'!$B$4 -> 5.25 | D39: 2.75 | E39: =C39+D39 -> 8 | F39: 0.5 | G39: 0 | H39: =E39+F39+G39 -> 8.5
A40: < 650 | B40: CRG-4 | C40: ='Repo rate'!$B$4 -> 5.25 | D40: 2.75 | E40: =C40+D40 -> 8 | F40: 2 | G40: -0.2 | H40: =E40+F40+G40 -> 9.8
A42: Condition | B42: Loan amount above Rs. 250 lakhs
A43: 800+ | B43: CRG-prime | C43: ='Repo rate'!$B$4 -> 5.25 | D43: 2.75 | E43: =C43+D43 -> 8 | F43: 0.05 | G43: -0.85 | H43: =E43+F43+G43 -> 7.2
A44: 750 - 799 | B44: CRG-1 | C44: ='Repo rate'!$B$4 -> 5.25 | D44: 2.75 | E44: =C44+D44 -> 8 | F44: 0.05 | G44: -0.85 | H44: =E44+F44+G44 -> 7.2
A45: 700 - 749 | B45: CRG-2 | C45: ='Repo rate'!$B$4 -> 5.25 | D45: 2.75 | E45: =C45+D45 -> 8 | F45: 0.1 | G45: -0.5 | H45: =E45+F45+G45 -> 7.6
A46: 650 - 699 | B46: CRG-3 | C46: ='Repo rate'!$B$4 -> 5.25 | D46: 2.75 | E46: =C46+D46 -> 8 | F46: 0.5 | G46: 0 | H46: =E46+F46+G46 -> 8.5
A47: < 650 | B47: CRG-4 | C47: ='Repo rate'!$B$4 -> 5.25 | D47: 2.75 | E47: =C47+D47 -> 8 | F47: 2 | G47: -0.3 | H47: =E47+F47+G47 -> 9.7
A52: Scheme | B52: HOUSING LOAN
A53: Loan type | B53: Term loan
E56: Fixed rate
A57: Irrespective of loan amount | C57: Repo Rate | D57: Markup | E57: Repo Linked Lending Rate | F57: Fixed Rate Premium (FRP) | G57: Credit Risk Premium | H57: Discount | I57: Final rate
A58: 800+ | B58: CRG-prime | C58: ='Repo rate'!$B$4 -> 5.25 | D58: 2.75 | E58: =C58+D58 -> 8 | F58: 0.75 | G58: 0.05 | H58: -0.25 | I58: =E58+G58+F58+H58 -> 8.55
A59: 750 - 799 | B59: CRG-1 | C59: ='Repo rate'!$B$4 -> 5.25 | D59: 2.75 | E59: =C59+D59 -> 8 | F59: 0.75 | G59: 0.05 | H59: 0 | I59: =E59+G59+F59+H59 -> 8.8
A60: 700 - 749 | B60: CRG-2 | C60: ='Repo rate'!$B$4 -> 5.25 | D60: 2.75 | E60: =C60+D60 -> 8 | F60: 0.75 | G60: 0.1 | H60: 0 | I60: =E60+G60+F60+H60 -> 8.85
A61: 650 - 699 | B61: CRG-3 | C61: ='Repo rate'!$B$4 -> 5.25 | D61: 2.75 | E61: =C61+D61 -> 8 | F61: 0.75 | G61: 0.5 | H61: 0 | I61: =E61+G61+F61+H61 -> 9.25
A62: < 650 | B62: CRG-4 | C62: ='Repo rate'!$B$4 -> 5.25 | D62: 2.75 | E62: =C62+D62 -> 8 | F62: 0.75 | G62: 2 | H62: 0 | I62: =E62+G62+F62+H62 -> 10.75
A66: Notes for | B66: HOUSING LOAN
A67: For Housing Loan (All variants) under CRG-Prime, CRG-1 & CRG-2, additional 5 bps concession for Takeover/Ready to move HL proposals & 5 bps concession for salaried employees working in Central/State Govt./PSUs/MNCs/Blue chip Companies & Corporates maintaining/switching salary a/c wth us including Canara SB Premium Payroll package payroll a/cs is applicable in all loan slabs.
A68: 0.05 concession for women borrowers across all the above list from top (Where only the CRP is changed by 0.05 only rest stays the same)

Sheet Indian Overseas Bank
A1: Bank | B1: Indian Overseas Bank
A2: Interest rate link | B2: https://www.iob.bank.in/en/Lending-Interest-Rates
A3: Credit score range given | B3: Yes
A4: Interest rates as per score | B4: Yes
A5: Gender split | B5: No
A6: Occupation split | B6: Yes
A7: Rate types | B7: Floating & Fixed
A8: Rate base | B8: Repo + Mark-up
A9: Special Govt. Employees | B9: Yes
A10: Loan Type - Term Loan | B10: Yes
A11: Loan Type - Overdraft | B11: No
A12: Top up | B12: Yes
A13: Rate varies by insurance | B13: No
A14: Updated as on | B14: 46217
A16: Scheme | B16: Subhagruha-Housing Loans
A17: Loan type | B17: Term loan
D19: Floating rate
D20: Repo Linked Lending Rate
B21: Repo Rate | C21: Markup | D21: Rate base | E21: Discount | F21: Final rate
A22: Occupation | B22: Salaried
A23: 800+ | B23: ='Repo rate'!$B$4 -> 5.25 | C23: 2.85 | D23: =B23+C23 -> 8.1 | E23: -0.9 | F23: =D23+E23 -> 7.2
A24: 775 - 799 | B24: ='Repo rate'!$B$4 -> 5.25 | C24: 2.85 | D24: =B24+C24 -> 8.1 | E24: -0.85 | F24: =D24+E24 -> 7.25
A25: 750 - 774 | B25: ='Repo rate'!$B$4 -> 5.25 | C25: 2.85 | D25: =B25+C25 -> 8.1 | E25: -0.55 | F25: =D25+E25 -> 7.55
A26: 725 - 749 | B26: ='Repo rate'!$B$4 -> 5.25 | C26: 2.85 | D26: =B26+C26 -> 8.1 | E26: -0.25 | F26: =D26+E26 -> 7.85
A27: 700 - 724 | B27: ='Repo rate'!$B$4 -> 5.25 | C27: 2.85 | D27: =B27+C27 -> 8.1 | E27: -0.15 | F27: =D27+E27 -> 7.95
A28: 680 - 699 | B28: ='Repo rate'!$B$4 -> 5.25 | C28: 2.85 | D28: =B28+C28 -> 8.1 | E28: 0.1 | F28: =D28+E28 -> 8.2
A29: -1 to 0 | B29: ='Repo rate'!$B$4 -> 5.25 | C29: 2.85 | D29: =B29+C29 -> 8.1 | E29: -0.25 | F29: =D29+E29 -> 7.85
A31: Occupation | B31: Self-Employed
A32: 800+ | B32: ='Repo rate'!$B$4 -> 5.25 | C32: 2.85 | D32: =B32+C32 -> 8.1 | E32: -0.8 | F32: =D32+E32 -> 7.3
A33: 775 - 799 | B33: ='Repo rate'!$B$4 -> 5.25 | C33: 2.85 | D33: =B33+C33 -> 8.1 | E33: -0.75 | F33: =D33+E33 -> 7.35
A34: 750 - 774 | B34: ='Repo rate'!$B$4 -> 5.25 | C34: 2.85 | D34: =B34+C34 -> 8.1 | E34: -0.45 | F34: =D34+E34 -> 7.65
A35: 725 - 749 | B35: ='Repo rate'!$B$4 -> 5.25 | C35: 2.85 | D35: =B35+C35 -> 8.1 | E35: -0.15 | F35: =D35+E35 -> 7.95
A36: 700 - 724 | B36: ='Repo rate'!$B$4 -> 5.25 | C36: 2.85 | D36: =B36+C36 -> 8.1 | E36: -0.05 | F36: =D36+E36 -> 8.05
A37: 680 - 699 | B37: ='Repo rate'!$B$4 -> 5.25 | C37: 2.85 | D37: =B37+C37 -> 8.1 | E37: 0.2 | F37: =D37+E37 -> 8.3
A38: -1 to 0 | B38: ='Repo rate'!$B$4 -> 5.25 | C38: 2.85 | D38: =B38+C38 -> 8.1 | E38: -0.15 | F38: =D38+E38 -> 7.95
A41: Scheme | B41: IOB HARIT SUBHAGRUHA (Green house)
A42: Loan type | B42: Term loan
D44: Floating rate
A45: Occupation | B45: Salaried
A46: 800+ | B46: ='Repo rate'!$B$4 -> 5.25 | C46: 2.85 | D46: =B46+C46 -> 8.1 | E46: -0.9 | F46: =D46+E46 -> 7.2
A47: 775 - 799 | B47: ='Repo rate'!$B$4 -> 5.25 | C47: 2.85 | D47: =B47+C47 -> 8.1 | E47: -0.9 | F47: =D47+E47 -> 7.2
A48: 750 - 774 | B48: ='Repo rate'!$B$4 -> 5.25 | C48: 2.85 | D48: =B48+C48 -> 8.1 | E48: -0.6 | F48: =D48+E48 -> 7.5
A49: 725 - 749 | B49: ='Repo rate'!$B$4 -> 5.25 | C49: 2.85 | D49: =B49+C49 -> 8.1 | E49: -0.3 | F49: =D49+E49 -> 7.8
A50: 700 - 724 | B50: ='Repo rate'!$B$4 -> 5.25 | C50: 2.85 | D50: =B50+C50 -> 8.1 | E50: -0.2 | F50: =D50+E50 -> 7.9
A51: 680 - 699 | B51: ='Repo rate'!$B$4 -> 5.25 | C51: 2.85 | D51: =B51+C51 -> 8.1 | E51: 0.05 | F51: =D51+E51 -> 8.15
A52: -1 to 0 | B52: ='Repo rate'!$B$4 -> 5.25 | C52: 2.85 | D52: =B52+C52 -> 8.1 | E52: -0.3 | F52: =D52+E52 -> 7.8
A54: Occupation | B54: Self-Employed
A55: 800+ | B55: ='Repo rate'!$B$4 -> 5.25 | C55: 2.85 | D55: =B55+C55 -> 8.1 | E55: -0.8 | F55: =D55+E55 -> 7.3
A56: 775 - 799 | B56: ='Repo rate'!$B$4 -> 5.25 | C56: 2.85 | D56: =B56+C56 -> 8.1 | E56: -0.8 | F56: =D56+E56 -> 7.3
A57: 750 - 774 | B57: ='Repo rate'!$B$4 -> 5.25 | C57: 2.85 | D57: =B57+C57 -> 8.1 | E57: -0.5 | F57: =D57+E57 -> 7.6
A58: 725 - 749 | B58: ='Repo rate'!$B$4 -> 5.25 | C58: 2.85 | D58: =B58+C58 -> 8.1 | E58: -0.2 | F58: =D58+E58 -> 7.9
A59: 700 - 724 | B59: ='Repo rate'!$B$4 -> 5.25 | C59: 2.85 | D59: =B59+C59 -> 8.1 | E59: -0.1 | F59: =D59+E59 -> 8
A60: 680 - 699 | B60: ='Repo rate'!$B$4 -> 5.25 | C60: 2.85 | D60: =B60+C60 -> 8.1 | E60: 0.15 | F60: =D60+E60 -> 8.25
A61: -1 to 0 | B61: ='Repo rate'!$B$4 -> 5.25 | C61: 2.85 | D61: =B61+C61 -> 8.1 | E61: -0.2 | F61: =D61+E61 -> 7.9
A63: Scheme | B63: Subhagruha Topup Loan
A64: Loan type | B64: Term loan
A65: Occupation | B65: Salaried & Self-Employed
A66: 800+ | B66: ='Repo rate'!$B$4 -> 5.25 | C66: 2.85 | D66: =B66+C66 -> 8.1 | E66: 1.55 | F66: =D66+E66 -> 9.65
A67: 775 - 799 | B67: ='Repo rate'!$B$4 -> 5.25 | C67: 2.85 | D67: =B67+C67 -> 8.1 | E67: 1.6 | F67: =D67+E67 -> 9.7
A68: 750 - 774 | B68: ='Repo rate'!$B$4 -> 5.25 | C68: 2.85 | D68: =B68+C68 -> 8.1 | E68: 1.65 | F68: =D68+E68 -> 9.75
A69: 725 - 749 | B69: ='Repo rate'!$B$4 -> 5.25 | C69: 2.85 | D69: =B69+C69 -> 8.1 | E69: 1.75 | F69: =D69+E69 -> 9.85
A70: 700 - 724 | B70: ='Repo rate'!$B$4 -> 5.25 | C70: 2.85 | D70: =B70+C70 -> 8.1 | E70: 1.95 | F70: =D70+E70 -> 10.05
A71: 680 - 699 | B71: ='Repo rate'!$B$4 -> 5.25 | C71: 2.85 | D71: =B71+C71 -> 8.1 | E71: 2.15 | F71: =D71+E71 -> 10.25
A72: -1 to 0 | B72: ='Repo rate'!$B$4 -> 5.25 | C72: 2.85 | D72: =B72+C72 -> 8.1 | E72: 1.75 | F72: =D72+E72 -> 9.85
A77: Fixed rate
A78: IOB HARIT SUBHAGRUHA (Green house)Subhagruha-Housing Loans | B78: 11
A79: Top up | B79: 12

Sheet Punjab & Sind Bank
A1: Bank | B1: Punjab & Sind bank
A2: Interest rate link | B2: https://punjabandsind.bank.in/content/prlr
A3: Credit score range given | B3: Yes
A4: Interest rates as per score | B4: Yes
A5: Gender split | B5: No
A6: Occupation split | B6: Yes
A7: Rate types | B7: Floating
A8: Rate base | B8: Repo + Mark-up
A9: Special Govt. Employees | B9: Yes
A10: Loan Type - Term Loan | B10: Yes
A11: Loan Type - Overdraft | B11: No
A12: Top up | B12: Yes
A13: Rate varies by insurance | B13: No
A14: Updated as on | B14: 46249
A15: Scheme | B15: PSB Apna Ghar
A16: Loan type | B16: Term loan
A17: Floating rate
D18: External Benchmark Linked Lending Rate (EBLR)
B19: Repo Rate | C19: Markup | D19: Rate base | E19: Credit Risk Premium | F19: Strategic Business Premium | G19: Final rate
A21: Occupation | B21: Salaried & Self-Employed
A22: 825+ | B22: ='Repo rate'!$B$4 -> 5.25 | C22: 2.1 | D22: =B22+C22 -> 7.35 | E22: 0 | F22: 0 | G22: =D22+E22+F22 -> 7.35
A23: 791 - 824 | B23: ='Repo rate'!$B$4 -> 5.25 | C23: 2.1 | D23: =B23+C23 -> 7.35 | E23: 0.04 | F23: 0.01 | G23: =D23+E23+F23 -> 7.4
A24: 750 - 790 | B24: ='Repo rate'!$B$4 -> 5.25 | C24: 2.1 | D24: =B24+C24 -> 7.35 | E24: 0.16 | F24: 0.04 | G24: =D24+E24+F24 -> 7.55
A25: 725 - 749 | B25: ='Repo rate'!$B$4 -> 5.25 | C25: 2.1 | D25: =B25+C25 -> 7.35 | E25: 0.29 | F25: 0.26 | G25: =D25+E25+F25 -> 7.9
A26: 700 - 724 | B26: ='Repo rate'!$B$4 -> 5.25 | C26: 2.1 | D26: =B26+C26 -> 7.35 | E26: 0.46 | F26: 0.44 | G26: =D26+E26+F26 -> 8.25
A27: 650 - 699 | B27: ='Repo rate'!$B$4 -> 5.25 | C27: 2.1 | D27: =B27+C27 -> 7.35 | E27: 0.95 | F27: 0.75 | G27: =D27+E27+F27 -> 9.05 | H27: Only for renewal loans
A28: < = 649 | B28: ='Repo rate'!$B$4 -> 5.25 | C28: 2.1 | D28: =B28+C28 -> 7.35 | E28: 2.62 | F28: 0.73 | G28: =D28+E28+F28 -> 10.7 | H28: Only for renewal loans
A30: Scheme | B30: PSB Apna Ghar Sahaj & Apna Ghar Gaurav (fort govt. employees)
A31: Loan type | B31: Term loan
A33: Occupation | B33: Salaried
A34: 825+ | B34: ='Repo rate'!$B$4 -> 5.25 | C34: 2.1 | D34: =B34+C34 -> 7.35 | E34: 0 | F34: 0 | G34: =D34+E34+F34 -> 7.35
A35: 791 - 824 | B35: ='Repo rate'!$B$4 -> 5.25 | C35: 2.1 | D35: =B35+C35 -> 7.35 | E35: 0.04 | F35: 0.01 | G35: =D35+E35+F35 -> 7.4
A36: 750 - 790 | B36: ='Repo rate'!$B$4 -> 5.25 | C36: 2.1 | D36: =B36+C36 -> 7.35 | E36: 0.16 | F36: 0.04 | G36: =D36+E36+F36 -> 7.55
A37: 725 - 749 | B37: ='Repo rate'!$B$4 -> 5.25 | C37: 2.1 | D37: =B37+C37 -> 7.35 | E37: 0.29 | F37: 0.26 | G37: =D37+E37+F37 -> 7.9
A38: 700 - 724 | B38: ='Repo rate'!$B$4 -> 5.25 | C38: 2.1 | D38: =B38+C38 -> 7.35 | E38: 0.46 | F38: 0.44 | G38: =D38+E38+F38 -> 8.25
A39: 650 - 699 | B39: ='Repo rate'!$B$4 -> 5.25 | C39: 2.1 | D39: =B39+C39 -> 7.35 | E39: 0.95 | F39: 0.75 | G39: =D39+E39+F39 -> 9.05 | H39: Only for renewal loans
A40: < = 649 | B40: ='Repo rate'!$B$4 -> 5.25 | C40: 2.1 | D40: =B40+C40 -> 7.35 | E40: 2.62 | F40: 0.73 | G40: =D40+E40+F40 -> 10.7 | H40: Only for renewal loans
A43: Scheme | B43: PSB Apna Ghar Top Up
A44: Loan type | B44: Term loan
A46: Occupation | B46: Salaried & Self-Employed
A47: 825+ | B47: ='Repo rate'!$B$4 -> 5.25 | C47: 2.1 | D47: =B47+C47 -> 7.35 | E47: 0 | F47: 1 | G47: =D47+E47+F47 -> 8.35
A48: 791 - 824 | B48: ='Repo rate'!$B$4 -> 5.25 | C48: 2.1 | D48: =B48+C48 -> 7.35 | E48: 0.04 | F48: 1.01 | G48: =D48+E48+F48 -> 8.4
A49: 750 - 790 | B49: ='Repo rate'!$B$4 -> 5.25 | C49: 2.1 | D49: =B49+C49 -> 7.35 | E49: 0.16 | F49: 1.04 | G49: =D49+E49+F49 -> 8.55
A50: 725 - 749 | B50: ='Repo rate'!$B$4 -> 5.25 | C50: 2.1 | D50: =B50+C50 -> 7.35 | E50: 0.29 | F50: 1.26 | G50: =D50+E50+F50 -> 8.9
A51: 700 - 724 | B51: ='Repo rate'!$B$4 -> 5.25 | C51: 2.1 | D51: =B51+C51 -> 7.35 | E51: 0.46 | F51: 1.44 | G51: =D51+E51+F51 -> 9.25
A52: 650 - 699 | B52: ='Repo rate'!$B$4 -> 5.25 | C52: 2.1 | D52: =B52+C52 -> 7.35 | E52: 0.95 | F52: 1.75 | G52: =D52+E52+F52 -> 10.05 | H52: Only for renewal loans
A53: < = 649 | B53: ='Repo rate'!$B$4 -> 5.25 | C53: 2.1 | D53: =B53+C53 -> 7.35 | E53: 2.62 | F53: 1.73 | G53: =D53+E53+F53 -> 11.7 | H53: Only for renewal loans

Sheet State Bank of India
A1: Bank | B1: State Bank of India
A2: Interest rate link | B2: https://homeloans.sbi.bank.in/products/view/regular-home-loan
A3: Credit score range given | B3: Yes | C3: Check there excel file for old rates for cibil range ion wesbite
A4: Interest rates as per score | B4: Yes | C4: From internal executives file - Dilip
A5: Gender split | B5: No
A6: Occupation split | B6: Yes
A7: Rate types | B7: Floating
A8: Rate base | B8: Repo + Mark-up
A9: Special Govt. Employees | B9: Yes
A10: Loan Type - Term Loan | B10: Yes
A11: Loan Type - Overdraft | B11: Yes
A12: Top up | B12: Yes
A13: Rate varies by insurance | B13: No
A14: Updated as on | B14: 46217
A16: Scheme | B16: Home Loan
A17: Loan type | B17: Term loan
D18: Floating rate
D19: External Benchmark Lending Rate
B20: Repo Rate | C20: Markup | D20: Rate base | E20: Discount | F20: Final rate
B22: Salaried
A23: 825+ | B23: ='Repo rate'!$B$4 -> 5.25 | C23: 2.65 | D23: =B23+C23 -> 7.9 | E23: -0.65 | F23: =D23+E23 -> 7.25
A24: 780 - 824 | B24: ='Repo rate'!$B$4 -> 5.25 | C24: 2.65 | D24: =B24+C24 -> 7.9 | E24: -0.3 | F24: =D24+E24 -> 7.6
A25: 750 - 779 | B25: ='Repo rate'!$B$4 -> 5.25 | C25: 2.65 | D25: =B25+C25 -> 7.9 | E25: -0.2 | F25: =D25+E25 -> 7.7
A26: 700 - 749 | B26: ='Repo rate'!$B$4 -> 5.25 | C26: 2.65 | D26: =B26+C26 -> 7.9 | E26: -0.1 | F26: =D26+E26 -> 7.8
A27: 650 - 699 | B27: ='Repo rate'!$B$4 -> 5.25 | C27: 2.65 | D27: =B27+C27 -> 7.9 | E27: =0.35 -> 0.35 | F27: =D27+E27 -> 8.25
A28: 550 - 649 | B28: ='Repo rate'!$B$4 -> 5.25 | C28: 2.65 | D28: =B28+C28 -> 7.9 | E28: 0.65 | F28: =D28+E28 -> 8.55
A29: 151 - 200 | B29: ='Repo rate'!$B$4 -> 5.25 | C29: 2.65 | D29: =B29+C29 -> 7.9 | E29: 0.45 | F29: =D29+E29 -> 8.35
A30: 101 - 150 | B30: ='Repo rate'!$B$4 -> 5.25 | C30: 2.65 | D30: =B30+C30 -> 7.9 | E30: 0.45 | F30: =D30+E30 -> 8.35
A31: NTC | B31: ='Repo rate'!$B$4 -> 5.25 | C31: 2.65 | D31: =B31+C31 -> 7.9 | E31: 0 | F31: =D31+E31 -> 7.9
B33: Repo Rate | C33: Markup | D33: Repo Linked Lending Rate | E33: Discount | F33: Final rate
B34: A | C34: B | D34: D = A + B | F34: D + E
A35: Occupation | B35: Self-Employed
A36: 825+ | B36: ='Repo rate'!$B$4 -> 5.25 | C36: 2.65 | D36: =B36+C36 -> 7.9 | E36: -0.65 | F36: =D36+E36 -> 7.25
A37: 780 - 824 | B37: ='Repo rate'!$B$4 -> 5.25 | C37: 2.65 | D37: =B37+C37 -> 7.9 | E37: -0.2 | F37: =D37+E37 -> 7.7
A38: 750 - 779 | B38: ='Repo rate'!$B$4 -> 5.25 | C38: 2.65 | D38: =B38+C38 -> 7.9 | E38: -0.1 | F38: =D38+E38 -> 7.8
A39: 700 - 749 | B39: ='Repo rate'!$B$4 -> 5.25 | C39: 2.65 | D39: =B39+C39 -> 7.9 | E39: 0 | F39: =D39+E39 -> 7.9
A40: 650 - 699 | B40: ='Repo rate'!$B$4 -> 5.25 | C40: 2.65 | D40: =B40+C40 -> 7.9 | E40: =0.45 -> 0.45 | F40: =D40+E40 -> 8.35
A41: 550 - 649 | B41: ='Repo rate'!$B$4 -> 5.25 | C41: 2.65 | D41: =B41+C41 -> 7.9 | E41: 0.75 | F41: =D41+E41 -> 8.65
A42: 151 - 200 | B42: ='Repo rate'!$B$4 -> 5.25 | C42: 2.65 | D42: =B42+C42 -> 7.9 | E42: 0.55 | F42: =D42+E42 -> 8.45
A43: 101 - 150 | B43: ='Repo rate'!$B$4 -> 5.25 | C43: 2.65 | D43: =B43+C43 -> 7.9 | E43: 0.55 | F43: =D43+E43 -> 8.45
A44: NTC | B44: ='Repo rate'!$B$4 -> 5.25 | C44: 2.65 | D44: =B44+C44 -> 7.9 | E44: 0.1 | F44: =D44+E44 -> 8
A47: Scheme | B47: Home loan Maxgain
A48: Loan type | B48: Overdraft
A51: Occupation | B51: Salaried & Self-Employed
A52: 825+ | B52: ='Repo rate'!$B$4 -> 5.25 | C52: 2.65 | D52: =B52+C52 -> 7.9 | E52: -0.15 | F52: =D52+E52 -> 7.75
A53: 780 - 824 | B53: ='Repo rate'!$B$4 -> 5.25 | C53: 2.65 | D53: =B53+C53 -> 7.9 | E53: 0.2 | F53: =D53+E53 -> 8.1
A54: 750 - 779 | B54: ='Repo rate'!$B$4 -> 5.25 | C54: 2.65 | D54: =B54+C54 -> 7.9 | E54: 0.3 | F54: =D54+E54 -> 8.2
A55: 700 - 749 | B55: ='Repo rate'!$B$4 -> 5.25 | C55: 2.65 | D55: =B55+C55 -> 7.9 | E55: 0.4 | F55: =D55+E55 -> 8.3
A56: 650 - 699 | B56: ='Repo rate'!$B$4 -> 5.25 | C56: 2.65 | D56: =B56+C56 -> 7.9 | E56: 0.85 | F56: =D56+E56 -> 8.75
A57: 550 - 649 | B57: ='Repo rate'!$B$4 -> 5.25 | C57: 2.65 | D57: =B57+C57 -> 7.9 | E57: 1.15 | F57: =D57+E57 -> 9.05
A58: 151 - 200 | B58: ='Repo rate'!$B$4 -> 5.25 | C58: 2.65 | D58: =B58+C58 -> 7.9 | E58: 0.85 | F58: =D58+E58 -> 8.75
A59: 101 - 150 | B59: ='Repo rate'!$B$4 -> 5.25 | C59: 2.65 | D59: =B59+C59 -> 7.9 | E59: 0.95 | F59: =D59+E59 -> 8.85
A60: NTC | B60: ='Repo rate'!$B$4 -> 5.25 | C60: 2.65 | D60: =B60+C60 -> 7.9 | E60: 0.5 | F60: =D60+E60 -> 8.4
A62: Scheme | B62: Top up loan
A63: Loan type | B63: Term loan
A67: Occupation | B67: Salaried
A68: 825+ | B68: ='Repo rate'!$B$4 -> 5.25 | C68: 2.65 | D68: =B68+C68 -> 7.9 | E68: -0.15 | F68: =D68+E68 -> 7.75
A69: 780 - 824 | B69: ='Repo rate'!$B$4 -> 5.25 | C69: 2.65 | D69: =B69+C69 -> 7.9 | E69: 1 | F69: =D69+E69 -> 8.9
A70: 750 - 779 | B70: ='Repo rate'!$B$4 -> 5.25 | C70: 2.65 | D70: =B70+C70 -> 7.9 | E70: 1.5 | F70: =D70+E70 -> 9.4
A71: 700 - 749 | B71: ='Repo rate'!$B$4 -> 5.25 | C71: 2.65 | D71: =B71+C71 -> 7.9 | E71: 2 | F71: =D71+E71 -> 9.9
A72: 650 - 699 | B72: ='Repo rate'!$B$4 -> 5.25 | C72: 2.65 | D72: =B72+C72 -> 7.9 | E72: 2.3 | F72: =D72+E72 -> 10.2
A73: 550 - 649 | B73: ='Repo rate'!$B$4 -> 5.25 | C73: 2.65 | D73: =B73+C73 -> 7.9 | E73: 2.6 | F73: =D73+E73 -> 10.5
A74: 151 - 200 | B74: ='Repo rate'!$B$4 -> 5.25 | C74: 2.65 | D74: =B74+C74 -> 7.9 | E74: 0.85 | F74: =D74+E74 -> 8.75
A75: 101 - 150 | B75: ='Repo rate'!$B$4 -> 5.25 | C75: 2.65 | D75: =B75+C75 -> 7.9 | E75: 0.95 | F75: =D75+E75 -> 8.85
A76: NTC | B76: ='Repo rate'!$B$4 -> 5.25 | C76: 2.65 | D76: =B76+C76 -> 7.9 | E76: 0.5 | F76: =D76+E76 -> 8.4
A80: Occupation | B80: Self-Employed
A81: 825+ | B81: ='Repo rate'!$B$4 -> 5.25 | C81: 2.65 | D81: =B81+C81 -> 7.9 | E81: -0.15 | F81: =D81+E81 -> 7.75
A82: 780 - 824 | B82: ='Repo rate'!$B$4 -> 5.25 | C82: 2.65 | D82: =B82+C82 -> 7.9 | E82: 1.1 | F82: =D82+E82 -> 9
A83: 750 - 779 | B83: ='Repo rate'!$B$4 -> 5.25 | C83: 2.65 | D83: =B83+C83 -> 7.9 | E83: 1.6 | F83: =D83+E83 -> 9.5
A84: 700 - 749 | B84: ='Repo rate'!$B$4 -> 5.25 | C84: 2.65 | D84: =B84+C84 -> 7.9 | E84: 2.1 | F84: =D84+E84 -> 10
A85: 650 - 699 | B85: ='Repo rate'!$B$4 -> 5.25 | C85: 2.65 | D85: =B85+C85 -> 7.9 | E85: 2.4 | F85: =D85+E85 -> 10.3
A86: 550 - 649 | B86: ='Repo rate'!$B$4 -> 5.25 | C86: 2.65 | D86: =B86+C86 -> 7.9 | E86: 2.7 | F86: =D86+E86 -> 10.6
A87: 151 - 200 | B87: ='Repo rate'!$B$4 -> 5.25 | C87: 2.65 | D87: =B87+C87 -> 7.9 | E87: 0.95 | F87: =D87+E87 -> 8.85
A88: 101 - 150 | B88: ='Repo rate'!$B$4 -> 5.25 | C88: 2.65 | D88: =B88+C88 -> 7.9 | E88: 1.05 | F88: =D88+E88 -> 8.95
A89: NTC | B89: ='Repo rate'!$B$4 -> 5.25 | C89: 2.65 | D89: =B89+C89 -> 7.9 | E89: 0.6 | F89: =D89+E89 -> 8.5
A91: Scheme | B91: Top up loan (Maxgain)
A92: Loan type | B92: Overdraft
A96: Occupation | B96: Salaried
A97: 825+ | B97: ='Repo rate'!$B$4 -> 5.25 | C97: 2.65 | D97: =B97+C97 -> 7.9 | E97: 0.35 | F97: =D97+E97 -> 8.25
A98: 780 - 824 | B98: ='Repo rate'!$B$4 -> 5.25 | C98: 2.65 | D98: =B98+C98 -> 7.9 | E98: 1.6 | F98: =D98+E98 -> 9.5
A99: 750 - 779 | B99: ='Repo rate'!$B$4 -> 5.25 | C99: 2.65 | D99: =B99+C99 -> 7.9 | E99: 2.1 | F99: =D99+E99 -> 10
A100: 700 - 749 | B100: ='Repo rate'!$B$4 -> 5.25 | C100: 2.65 | D100: =B100+C100 -> 7.9 | E100: 2.6 | F100: =D100+E100 -> 10.5
A101: 650 - 699 | B101: ='Repo rate'!$B$4 -> 5.25 | C101: 2.65 | D101: =B101+C101 -> 7.9 | E101: 2.9 | F101: =D101+E101 -> 10.8
A102: 550 - 649 | B102: ='Repo rate'!$B$4 -> 5.25 | C102: 2.65 | D102: =B102+C102 -> 7.9 | E102: 3.2 | F102: =D102+E102 -> 11.1
A103: 151 - 200 | B103: ='Repo rate'!$B$4 -> 5.25 | C103: 2.65 | D103: =B103+C103 -> 7.9 | E103: 1.45 | F103: =D103+E103 -> 9.35
A104: 101 - 150 | B104: ='Repo rate'!$B$4 -> 5.25 | C104: 2.65 | D104: =B104+C104 -> 7.9 | E104: 1.55 | F104: =D104+E104 -> 9.45
A105: NTC | B105: ='Repo rate'!$B$4 -> 5.25 | C105: 2.65 | D105: =B105+C105 -> 7.9 | E105: 1.1 | F105: =D105+E105 -> 9
A109: Occupation | B109: Self-Employed
A110: 825+ | B110: ='Repo rate'!$B$4 -> 5.25 | C110: 2.65 | D110: =B110+C110 -> 7.9 | E110: 0.35 | F110: =D110+E110 -> 8.25
A111: 780 - 824 | B111: ='Repo rate'!$B$4 -> 5.25 | C111: 2.65 | D111: =B111+C111 -> 7.9 | E111: 1.7 | F111: =D111+E111 -> 9.6
A112: 750 - 779 | B112: ='Repo rate'!$B$4 -> 5.25 | C112: 2.65 | D112: =B112+C112 -> 7.9 | E112: 2.2 | F112: =D112+E112 -> 10.1
A113: 700 - 749 | B113: ='Repo rate'!$B$4 -> 5.25 | C113: 2.65 | D113: =B113+C113 -> 7.9 | E113: 2.7 | F113: =D113+E113 -> 10.6
A114: 650 - 699 | B114: ='Repo rate'!$B$4 -> 5.25 | C114: 2.65 | D114: =B114+C114 -> 7.9 | E114: 3 | F114: =D114+E114 -> 10.9
A115: 550 - 649 | B115: ='Repo rate'!$B$4 -> 5.25 | C115: 2.65 | D115: =B115+C115 -> 7.9 | E115: 3.3 | F115: =D115+E115 -> 11.2
A116: 151 - 200 | B116: ='Repo rate'!$B$4 -> 5.25 | C116: 2.65 | D116: =B116+C116 -> 7.9 | E116: 1.55 | F116: =D116+E116 -> 9.45
A117: 101 - 150 | B117: ='Repo rate'!$B$4 -> 5.25 | C117: 2.65 | D117: =B117+C117 -> 7.9 | E117: 1.65 | F117: =D117+E117 -> 9.55
A118: NTC | B118: ='Repo rate'!$B$4 -> 5.25 | C118: 2.65 | D118: =B118+C118 -> 7.9 | E118: 1.2 | F118: =D118+E118 -> 9.1

Sheet Bank of Maharashtra
A1: Bank | B1: Bank of Maharastra
A2: Interest rate link | B2: https://bankofmaharashtra.bank.in/retail-interest-rates
A3: Credit score range given | B3: Yes
A4: Interest rates as per score | B4: Yes
A5: Gender split | B5: Yes
A6: Occupation split | B6: Yes
A7: Rate types | B7: Floating & Fixed
A8: Rate base | B8: Repo + Mark-up
A9: Special Govt. Employees | B9: No | C9: Not included as only one slab
A10: Loan Type - Term Loan | B10: Yes
A11: Loan Type - Overdraft | B11: Yes
A12: Top up | B12: Yes
A13: Rate varies by insurance | B13: No
A14: Updated as on | B14: 46249
A16: Scheme | B16: Maha Super Housing Loan Scheme
A17: Loan type | B17: Term loan
D18: Floating rate
D19: Repo Linked Lending Rate
B20: Repo Rate | C20: Markup | D20: rate base | E20: Discount | F20: Final rate
A22: Occupation | B22: Salaried
A23: 800+ | B23: ='Repo rate'!$B$4 -> 5.25 | C23: 2.8 | D23: =B23+C23 -> 8.05 | E23: -1.05 | F23: =D23+E23 -> 7
A24: 750 - 799 | B24: ='Repo rate'!$B$4 -> 5.25 | C24: 2.8 | D24: =B24+C24 -> 8.05 | E24: -0.8 | F24: =D24+E24 -> 7.25
A25: 725 - 749 | B25: ='Repo rate'!$B$4 -> 5.25 | C25: 2.8 | D25: =B25+C25 -> 8.05 | E25: -0.35 | F25: =D25+E25 -> 7.7
A26: 700 - 724 | B26: ='Repo rate'!$B$4 -> 5.25 | C26: 2.8 | D26: =B26+C26 -> 8.05 | E26: -0.3 | F26: =D26+E26 -> 7.75
A27: 650 - 699 | B27: ='Repo rate'!$B$4 -> 5.25 | C27: 2.8 | D27: =B27+C27 -> 8.05 | E27: 0.3 | F27: =D27+E27 -> 8.35
A28: 600 - 649 | B28: ='Repo rate'!$B$4 -> 5.25 | C28: 2.8 | D28: =B28+C28 -> 8.05 | E28: 0.7 | F28: =D28+E28 -> 8.75
A29: < 600 | B29: ='Repo rate'!$B$4 -> 5.25 | C29: 2.8 | D29: =B29+C29 -> 8.05 | E29: 1.1 | F29: =D29+E29 -> 9.15
A30: NTC | B30: ='Repo rate'!$B$4 -> 5.25 | C30: 2.8 | D30: =B30+C30 -> 8.05 | E30: -0.35 | F30: =D30+E30 -> 7.7
A32: Occupation | B32: Self-Employed
A33: 800+ | B33: ='Repo rate'!$B$4 -> 5.25 | C33: 2.8 | D33: =B33+C33 -> 8.05 | E33: -0.95 | F33: =D33+E33 -> 7.1
A34: 750 - 799 | B34: ='Repo rate'!$B$4 -> 5.25 | C34: 2.8 | D34: =B34+C34 -> 8.05 | E34: -0.7 | F34: =D34+E34 -> 7.35
A35: 725 - 749 | B35: ='Repo rate'!$B$4 -> 5.25 | C35: 2.8 | D35: =B35+C35 -> 8.05 | E35: -0.25 | F35: =D35+E35 -> 7.8
A36: 700 - 724 | B36: ='Repo rate'!$B$4 -> 5.25 | C36: 2.8 | D36: =B36+C36 -> 8.05 | E36: -0.1 | F36: =D36+E36 -> 7.95
A37: 650 - 699 | B37: ='Repo rate'!$B$4 -> 5.25 | C37: 2.8 | D37: =B37+C37 -> 8.05 | E37: 0.5 | F37: =D37+E37 -> 8.55
A38: 600 - 649 | B38: ='Repo rate'!$B$4 -> 5.25 | C38: 2.8 | D38: =B38+C38 -> 8.05 | E38: 0.9 | F38: =D38+E38 -> 8.95
A39: < 600 | B39: ='Repo rate'!$B$4 -> 5.25 | C39: 2.8 | D39: =B39+C39 -> 8.05 | E39: 1.6 | F39: =D39+E39 -> 9.65
A40: NTC | B40: ='Repo rate'!$B$4 -> 5.25 | C40: 2.8 | D40: =B40+C40 -> 8.05 | E40: -0.15 | F40: =D40+E40 -> 7.9
A43: Scheme | B43: Maha Super Green Building (For green building)
A44: Loan type | B44: Term loan
A46: Occupation | B46: Salaried
A47: 800+ | B47: ='Repo rate'!$B$4 -> 5.25 | C47: 2.8 | D47: =B47+C47 -> 8.05 | E47: -0.95 | F47: =D47+E47 -> 7.1
A48: 750 - 799 | B48: ='Repo rate'!$B$4 -> 5.25 | C48: 2.8 | D48: =B48+C48 -> 8.05 | E48: -0.8 | F48: =D48+E48 -> 7.25
A49: 725 - 749 | B49: ='Repo rate'!$B$4 -> 5.25 | C49: 2.8 | D49: =B49+C49 -> 8.05 | E49: -0.35 | F49: =D49+E49 -> 7.7
A50: 700 - 724 | B50: ='Repo rate'!$B$4 -> 5.25 | C50: 2.8 | D50: =B50+C50 -> 8.05 | E50: -0.4 | F50: =D50+E50 -> 7.65
A51: 650 - 699 | B51: ='Repo rate'!$B$4 -> 5.25 | C51: 2.8 | D51: =B51+C51 -> 8.05 | E51: 0.2 | F51: =D51+E51 -> 8.25
A52: 600 - 649 | B52: ='Repo rate'!$B$4 -> 5.25 | C52: 2.8 | D52: =B52+C52 -> 8.05 | E52: 0.6 | F52: =D52+E52 -> 8.65
A53: < 600 | B53: ='Repo rate'!$B$4 -> 5.25 | C53: 2.8 | D53: =B53+C53 -> 8.05 | E53: 1 | F53: =D53+E53 -> 9.05
A54: NTC | B54: ='Repo rate'!$B$4 -> 5.25 | C54: 2.8 | D54: =B54+C54 -> 8.05 | E54: -0.45 | F54: =D54+E54 -> 7.6
A56: Occupation | B56: Self-Employed
A57: 800+ | B57: ='Repo rate'!$B$4 -> 5.25 | C57: 2.8 | D57: =B57+C57 -> 8.05 | E57: -0.85 | F57: =D57+E57 -> 7.2
A58: 750 - 799 | B58: ='Repo rate'!$B$4 -> 5.25 | C58: 2.8 | D58: =B58+C58 -> 8.05 | E58: -0.7 | F58: =D58+E58 -> 7.35
A59: 725 - 749 | B59: ='Repo rate'!$B$4 -> 5.25 | C59: 2.8 | D59: =B59+C59 -> 8.05 | E59: -0.25 | F59: =D59+E59 -> 7.8
A60: 700 - 724 | B60: ='Repo rate'!$B$4 -> 5.25 | C60: 2.8 | D60: =B60+C60 -> 8.05 | E60: -0.2 | F60: =D60+E60 -> 7.85
A61: 650 - 699 | B61: ='Repo rate'!$B$4 -> 5.25 | C61: 2.8 | D61: =B61+C61 -> 8.05 | E61: 0.4 | F61: =D61+E61 -> 8.45
A62: 600 - 649 | B62: ='Repo rate'!$B$4 -> 5.25 | C62: 2.8 | D62: =B62+C62 -> 8.05 | E62: 0.8 | F62: =D62+E62 -> 8.85
A63: < 600 | B63: ='Repo rate'!$B$4 -> 5.25 | C63: 2.8 | D63: =B63+C63 -> 8.05 | E63: 1.5 | F63: =D63+E63 -> 9.55
A64: NTC | B64: ='Repo rate'!$B$4 -> 5.25 | C64: 2.8 | D64: =B64+C64 -> 8.05 | E64: -0.25 | F64: =D64+E64 -> 7.8
A66: Scheme | B66: Maha Super Flexi Housing Loan Scheme
A67: Loan type | B67: Overdraft
A70: Occupation | B70: Salaried
A71: 800+ | B71: ='Repo rate'!$B$4 -> 5.25 | C71: 2.8 | D71: =B71+C71 -> 8.05 | E71: -0.8 | F71: =D71+E71 -> 7.25
A72: 750 - 799 | B72: ='Repo rate'!$B$4 -> 5.25 | C72: 2.8 | D72: =B72+C72 -> 8.05 | E72: -0.55 | F72: =D72+E72 -> 7.5
A73: 725 - 749 | B73: ='Repo rate'!$B$4 -> 5.25 | C73: 2.8 | D73: =B73+C73 -> 8.05 | E73: -0.1 | F73: =D73+E73 -> 7.95
A74: 700 - 724 | B74: ='Repo rate'!$B$4 -> 5.25 | C74: 2.8 | D74: =B74+C74 -> 8.05 | E74: -0.05 | F74: =D74+E74 -> 8
A75: 650 - 699 | B75: ='Repo rate'!$B$4 -> 5.25 | C75: 2.8 | D75: =B75+C75 -> 8.05 | E75: 0.55 | F75: =D75+E75 -> 8.6
A76: 600 - 649 | B76: ='Repo rate'!$B$4 -> 5.25 | C76: 2.8 | D76: =B76+C76 -> 8.05 | E76: 0.95 | F76: =D76+E76 -> 9
A77: < 600 | B77: ='Repo rate'!$B$4 -> 5.25 | C77: 2.8 | D77: =B77+C77 -> 8.05 | E77: 1.35 | F77: =D77+E77 -> 9.4
A78: NTC | B78: ='Repo rate'!$B$4 -> 5.25 | C78: 2.8 | D78: =B78+C78 -> 8.05 | E78: -0.1 | F78: =D78+E78 -> 7.95
A80: Scheme | B80: Maha Super Flexi Housing Loan Scheme
A81: Loan type | B81: Overdraft
A82: Occupation | B82: Self - Employed
A83: 800+ | B83: ='Repo rate'!$B$4 -> 5.25 | C83: 2.8 | D83: =B83+C83 -> 8.05 | E83: -0.7 | F83: =D83+E83 -> 7.35
A84: 750 - 799 | B84: ='Repo rate'!$B$4 -> 5.25 | C84: 2.8 | D84: =B84+C84 -> 8.05 | E84: -0.45 | F84: =D84+E84 -> 7.6
A85: 725 - 749 | B85: ='Repo rate'!$B$4 -> 5.25 | C85: 2.8 | D85: =B85+C85 -> 8.05 | E85: 0 | F85: =D85+E85 -> 8.05
A86: 700 - 724 | B86: ='Repo rate'!$B$4 -> 5.25 | C86: 2.8 | D86: =B86+C86 -> 8.05 | E86: 0.15 | F86: =D86+E86 -> 8.2
A87: 650 - 699 | B87: ='Repo rate'!$B$4 -> 5.25 | C87: 2.8 | D87: =B87+C87 -> 8.05 | E87: 0.75 | F87: =D87+E87 -> 8.8
A88: 600 - 649 | B88: ='Repo rate'!$B$4 -> 5.25 | C88: 2.8 | D88: =B88+C88 -> 8.05 | E88: 1.15 | F88: =D88+E88 -> 9.2
A89: < 600 | B89: ='Repo rate'!$B$4 -> 5.25 | C89: 2.8 | D89: =B89+C89 -> 8.05 | E89: 1.85 | F89: =D89+E89 -> 9.9
A90: NTC | B90: ='Repo rate'!$B$4 -> 5.25 | C90: 2.8 | D90: =B90+C90 -> 8.05 | E90: 0.1 | F90: =D90+E90 -> 8.15
A93: Scheme | B93: Maha Bank Top Up Loan Scheme
A94: Loan type | B94: Term loan
A95: Floating rate
A96: Occupation | B96: Salaried
A97: 800+ | B97: ='Repo rate'!$B$4 -> 5.25 | C97: 2.8 | D97: =B97+C97 -> 8.05 | E97: -0.65 | F97: =D97+E97 -> 7.4
A98: 750 - 799 | B98: ='Repo rate'!$B$4 -> 5.25 | C98: 2.8 | D98: =B98+C98 -> 8.05 | E98: -0.05 | F98: =D98+E98 -> 8
A99: 725 - 749 | B99: ='Repo rate'!$B$4 -> 5.25 | C99: 2.8 | D99: =B99+C99 -> 8.05 | E99: 0.65 | F99: =D99+E99 -> 8.7
A100: 700 - 724 | B100: ='Repo rate'!$B$4 -> 5.25 | C100: 2.8 | D100: =B100+C100 -> 8.05 | E100: 0.7 | F100: =D100+E100 -> 8.75
A101: 681 - 699 | B101: ='Repo rate'!$B$4 -> 5.25 | C101: 2.8 | D101: =B101+C101 -> 8.05 | E101: 1.3 | F101: =D101+E101 -> 9.35
A102: 650 - 680 | B102: ='Repo rate'!$B$4 -> 5.25 | C102: 2.8 | D102: =B102+C102 -> 8.05 | E102: 3.3 | F102: =D102+E102 -> 11.35
A103: 600 - 649 | B103: ='Repo rate'!$B$4 -> 5.25 | C103: 2.8 | D103: =B103+C103 -> 8.05 | E103: 3.7 | F103: =D103+E103 -> 11.75
A104: < 600 | B104: ='Repo rate'!$B$4 -> 5.25 | C104: 2.8 | D104: =B104+C104 -> 8.05 | E104: 4.1 | F104: =D104+E104 -> 12.15
A105: NTC | B105: ='Repo rate'!$B$4 -> 5.25 | C105: 2.8 | D105: =B105+C105 -> 8.05 | E105: 2.65 | F105: =D105+E105 -> 10.7
A107: Occupation | B107: Self-Employed
A108: 800+ | B108: ='Repo rate'!$B$4 -> 5.25 | C108: 2.8 | D108: =B108+C108 -> 8.05 | E108: -0.45 | F108: =D108+E108 -> 7.6
A109: 750 - 799 | B109: ='Repo rate'!$B$4 -> 5.25 | C109: 2.8 | D109: =B109+C109 -> 8.05 | E109: 0.05 | F109: =D109+E109 -> 8.1
A110: 725 - 749 | B110: ='Repo rate'!$B$4 -> 5.25 | C110: 2.8 | D110: =B110+C110 -> 8.05 | E110: 0.75 | F110: =D110+E110 -> 8.8
A111: 700 - 724 | B111: ='Repo rate'!$B$4 -> 5.25 | C111: 2.8 | D111: =B111+C111 -> 8.05 | E111: 0.9 | F111: =D111+E111 -> 8.95
A112: 681 - 699 | B112: ='Repo rate'!$B$4 -> 5.25 | C112: 2.8 | D112: =B112+C112 -> 8.05 | E112: 1.5 | F112: =D112+E112 -> 9.55
A113: 650 - 680 | B113: ='Repo rate'!$B$4 -> 5.25 | C113: 2.8 | D113: =B113+C113 -> 8.05 | E113: 3.5 | F113: =D113+E113 -> 11.55
A114: 600 - 649 | B114: ='Repo rate'!$B$4 -> 5.25 | C114: 2.8 | D114: =B114+C114 -> 8.05 | E114: 3.9 | F114: =D114+E114 -> 11.95
...

Sheet UCO Bank
A1: Bank | B1: UCO Bank
A2: Interest rate link | B2: https://www.uco.bank.in/repo
A3: Credit score range given | B3: Yes
A4: Interest rates as per score | B4: Yes
A5: Gender split | B5: Yes
A6: Occupation split | B6: No
A7: Rate types | B7: Floating
A8: Rate base | B8: Repo + Mark-up
A9: Special Govt. Employees | B9: No
A10: Loan Type - Term Loan | B10: Yes
A11: Loan Type - Overdraft | B11: No
A12: Top up | B12: Yes
A13: Rate varies by insurance | B13: No
A14: Updated as on | B14: 46217
A17: Scheme | B17: UCO Home
A18: Loan type | B18: Term loan
D19: Floating rate
D21: Repo Linked Lending Rate
B22: Repo Rate | C22: Markup | D22: rate base | E22: Spread | F22: Startegic Discount | G22: Final rate
A25: 850+ | B25: ='Repo rate'!$B$4 -> 5.25 | C25: 2.8 | D25: =B25+C25 -> 8.05 | E25: 0.05 | F25: -0.95 | G25: =D25+F25+E25 -> 7.15
A26: 825 - 849 | B26: ='Repo rate'!$B$4 -> 5.25 | C26: 2.8 | D26: =B26+C26 -> 8.05 | E26: 0.15 | F26: -0.95 | G26: =D26+F26+E26 -> 7.25
A27: 800 - 824 | B27: ='Repo rate'!$B$4 -> 5.25 | C27: 2.8 | D27: =B27+C27 -> 8.05 | E27: 0.25 | F27: -0.95 | G27: =D27+F27+E27 -> 7.35
A28: 750 - 799 | B28: ='Repo rate'!$B$4 -> 5.25 | C28: 2.8 | D28: =B28+C28 -> 8.05 | E28: 0.45 | F28: -0.95 | G28: =D28+F28+E28 -> 7.55
A29: 700 - 749 | B29: ='Repo rate'!$B$4 -> 5.25 | C29: 2.8 | D29: =B29+C29 -> 8.05 | E29: 0.75 | F29: -0.95 | G29: =D29+F29+E29 -> 7.85
A30: 650 - 699 | B30: ='Repo rate'!$B$4 -> 5.25 | C30: 2.8 | D30: =B30+C30 -> 8.05 | E30: 0.8 | F30: 0 | G30: =D30+F30+E30 -> 8.85
A31: 600 - 649 | B31: ='Repo rate'!$B$4 -> 5.25 | C31: 2.8 | D31: =B31+C31 -> 8.05 | E31: 1.2 | F31: 0 | G31: =D31+F31+E31 -> 9.25
A32: 0-1 or <300 | B32: ='Repo rate'!$B$4 -> 5.25 | C32: 2.8 | D32: =B32+C32 -> 8.05 | E32: 0.3 | F32: 0 | G32: =D32+F32+E32 -> 8.35
A35: Scheme | B35: UCO Top Up Home Loan
A36: Loan type | B36: Term loan
A38: Occupation | B38: Salaried & Self-Employed
A39: 850+ | B39: ='Repo rate'!$B$4 -> 5.25 | C39: 2.8 | D39: =B39+C39 -> 8.05 | E39: 0.1 | F39: 0 | G39: =D39+F39+E39 -> 8.15
A40: 825 - 849 | B40: ='Repo rate'!$B$4 -> 5.25 | C40: 2.8 | D40: =B40+C40 -> 8.05 | E40: 0.45 | F40: 0 | G40: =D40+F40+E40 -> 8.5
A41: 800 - 824 | B41: ='Repo rate'!$B$4 -> 5.25 | C41: 2.8 | D41: =B41+C41 -> 8.05 | E41: 0.7 | F41: 0 | G41: =D41+F41+E41 -> 8.75
A42: 750 - 799 | B42: ='Repo rate'!$B$4 -> 5.25 | C42: 2.8 | D42: =B42+C42 -> 8.05 | E42: 1.05 | F42: 0 | G42: =D42+F42+E42 -> 9.1
A43: 700 - 749 | B43: ='Repo rate'!$B$4 -> 5.25 | C43: 2.8 | D43: =B43+C43 -> 8.05 | E43: 1.2 | F43: 0 | G43: =D43+F43+E43 -> 9.25
A44: 650 - 699 | B44: ='Repo rate'!$B$4 -> 5.25 | C44: 2.8 | D44: =B44+C44 -> 8.05 | E44: 2.7 | F44: 0 | G44: =D44+F44+E44 -> 10.75
A46: Notes for | B46: UCO Home
A47: Addl. Concession Women Borrower - 0.05
A48: Addl. Concession Takeover - 0.1

Sheet Jammu & Kashmir Bank
A1: Bank | B1: Jammu & Kashmir Bank
A2: Interest rate link | B2: https://jkb.bank.in/housing-loans
A3: Credit score range given | B3: Yes
A4: Interest rates as per score | B4: Yes
A5: Gender split | B5: No
A6: Occupation split | B6: No
A7: Rate types | B7: Floating
A8: Rate base | B8: Repo + Mark-up
A9: Special Govt. Employees | B9: No
A10: Loan Type - Term Loan | B10: Yes
A11: Loan Type - Overdraft | B11: No
A12: Top up | B12: No
A13: Rate varies by insurance | B13: No
A14: Updated as on | B14: 46217
A15: Scheme | B15: Housing Loan
A16: Loan type | B16: Term loan
A17: Floating rate
D18: Housing Loan Repo Linked Lending Rate (HLRLLR)
B19: Repo Rate | C19: Markup | D19: Rate base | E19: Discount | F19: Final rate
A21: Occupation | B21: Salaried & Self-Employed
A22: 750+ | B22: ='Repo rate'!$B$4 -> 5.25 | C22: 2.6 | D22: =B22+C22 -> 7.85 | E22: -0.35 | F22: =D22+E22 -> 7.5
A23: 726 - 749 | B23: ='Repo rate'!$B$4 -> 5.25 | C23: 2.6 | D23: =B23+C23 -> 7.85 | E23: -0.25 | F23: =D23+E23 -> 7.6
A24: 701 - 725 | B24: ='Repo rate'!$B$4 -> 5.25 | C24: 2.6 | D24: =B24+C24 -> 7.85 | E24: -0.15 | F24: =D24+E24 -> 7.7
A25: 675 - 700 | B25: ='Repo rate'!$B$4 -> 5.25 | C25: 2.6 | D25: =B25+C25 -> 7.85 | E25: 0.1 | F25: =D25+E25 -> 7.95
A26: < 675 | B26: ='Repo rate'!$B$4 -> 5.25 | C26: 2.6 | D26: =B26+C26 -> 7.85 | E26: 0.35 | F26: =D26+E26 -> 8.2

Sheet DCB Bank
A1: Bank | B1: DCB Bank
A2: Interest rate link | B2: https://www.dcb.bank.in/rates/lending-rates
A3: Credit score range given | B3: No
A4: Interest rates as per score | B4: No
A5: Gender split | B5: No
A6: Occupation split | B6: No
A7: Rate types | B7: Floating
A8: Rate base | B8: Repo + Mark-up
A9: Special Govt. Employees | B9: No
A10: Loan Type - Term Loan | B10: Yes
A11: Loan Type - Overdraft | B11: No
A12: Top up | B12: No
A13: Rate varies by insurance | B13: No
A14: Updated as on | B14: 46217
A16: Scheme | B16: Home Loan
A17: Loan type | B17: Term loan
D18: Floating rate
D19: Repo Linked Lending Rate (RLLR)
B20: Repo Rate | C20: Markup | D20: rate base | E20: Discount | F20: Final rate
A22: occupation | B22: Salaried & Self-Employed
A23: 800+ | B23: ='Repo rate'!$B$4 -> 5.25 | C23: 4.83 | D23: =B23+C23 -> 10.08 | E23: -0.33 | F23: =D23+E23 -> 9.75
A24: 750 - 799 | B24: ='Repo rate'!$B$4 -> 5.25 | C24: 4.83 | D24: =B24+C24 -> 10.08 | E24: -0.18 | F24: =D24+E24 -> 9.9
A25: 700 - 749 | B25: ='Repo rate'!$B$4 -> 5.25 | C25: 4.83 | D25: =B25+C25 -> 10.08 | E25: 0.07 | F25: =D25+E25 -> 10.15
A26: 650 - 699 | B26: ='Repo rate'!$B$4 -> 5.25 | C26: 4.83 | D26: =B26+C26 -> 10.08 | E26: 0.22 | F26: =D26+E26 -> 10.3
A27: 600 - 649 | B27: ='Repo rate'!$B$4 -> 5.25 | C27: 4.83 | D27: =B27+C27 -> 10.08 | E27: 0.45 | F27: =D27+E27 -> 10.53
A28: < 600 | B28: ='Repo rate'!$B$4 -> 5.25 | C28: 4.83 | D28: =B28+C28 -> 10.08 | E28: 0.57 | F28: =D28+E28 -> 10.65

Sheet Indian Bank
A1: Bank | B1: Indian Bank
A2: Interest rate link | B2: https://indianbank.bank.in/en/interest-rates-on-personal-segment-loan-products#!
A3: Credit score range given | B3: No
A4: Interest rates as per score | B4: No
A5: Gender split | B5: No
A6: Occupation split | B6: No
A7: Rate types | B7: Floating
A8: Rate base | B8: Repo + Mark-up
A9: Special Govt. Employees | B9: No
A10: Loan Type - Term Loan | B10: Yes
A11: Loan Type - Overdraft | B11: Yes
A12: Top up | B12: No
A13: Rate varies by insurance | B13: No
A14: Updated as on | B14: 46217
A17: Scheme | B17: IB Home Loan
A18: Loan type | B18: Term loan
D19: Floating rate
D20: External Benchmark Lending Rate
B21: Repo Rate | C21: Markup | D21: rate base | E21: Discount | F21: Final rate
A23: Occupation | B23: Salaried & Self-Employed
A24: 800+ | B24: ='Repo rate'!$B$4 -> 5.25 | C24: 2.7 | D24: =B24+C24 -> 7.95 | E24: -0.8 | F24: =D24+E24 -> 7.15
A25: 750 - 799 | B25: ='Repo rate'!$B$4 -> 5.25 | C25: 2.7 | D25: =B25+C25 -> 7.95 | E25: -0.5 | F25: =D25+E25 -> 7.45
A26: 700 - 749 | B26: ='Repo rate'!$B$4 -> 5.25 | C26: 2.7 | D26: =B26+C26 -> 7.95 | E26: -0.2 | F26: =D26+E26 -> 7.75
A27: 650 - 699 | B27: ='Repo rate'!$B$4 -> 5.25 | C27: 2.7 | D27: =B27+C27 -> 7.95 | E27: 0 | F27: =D27+E27 -> 7.95
A28: 600 - 649 | B28: ='Repo rate'!$B$4 -> 5.25 | C28: 2.7 | D28: =B28+C28 -> 7.95 | E28: 0.2 | F28: =D28+E28 -> 8.15
A29: < 600 | B29: ='Repo rate'!$B$4 -> 5.25 | C29: 2.7 | D29: =B29+C29 -> 7.95 | E29: 0.6 | F29: =D29+E29 -> 8.55
A32: Scheme | B32: IB Home Loan Flexi
A33: Loan type | B33: Overdraft
D34: Floating rate
A36: Occupation | B36: Salaried & Self-Employed
A37: 800+ | B37: ='Repo rate'!$B$4 -> 5.25 | C37: 2.7 | D37: =B37+C37 -> 7.95 | E37: -0.4 | F37: =D37+E37 -> 7.55
A38: 750 - 799 | B38: ='Repo rate'!$B$4 -> 5.25 | C38: 2.7 | D38: =B38+C38 -> 7.95 | E38: -0.1 | F38: =D38+E38 -> 7.85
A39: 700 - 749 | B39: ='Repo rate'!$B$4 -> 5.25 | C39: 2.7 | D39: =B39+C39 -> 7.95 | E39: 0.2 | F39: =D39+E39 -> 8.15
A40: 650 - 699 | B40: ='Repo rate'!$B$4 -> 5.25 | C40: 2.7 | D40: =B40+C40 -> 7.95 | E40: 0.4 | F40: =D40+E40 -> 8.35
A41: 600 - 649 | B41: ='Repo rate'!$B$4 -> 5.25 | C41: 2.7 | D41: =B41+C41 -> 7.95 | E41: 0.6 | F41: =D41+E41 -> 8.55
A42: < 600 | B42: ='Repo rate'!$B$4 -> 5.25 | C42: 2.7 | D42: =B42+C42 -> 7.95 | E42: 1 | F42: =D42+E42 -> 8.95

Sheet Bandhan Bank
A1: Bank | B1: Bandhan Bank
A2: Interest rate link | B2: https://bandhan.bank.in/personal/home-loan/suraksha#rctabtwo
A3: Credit score range given | B3: No
A4: Interest rates as per score | B4: No
A5: Gender split | B5: No
A6: Occupation split | B6: No
A7: Rate types | B7: Floating
A8: Rate base | B8: Repo
A9: Special Govt. Employees | B9: No
A10: Loan Type - Term Loan | B10: Yes
A11: Loan Type - Overdraft | B11: No
A12: Top up | B12: No
A13: Rate varies by insurance | B13: No
A14: Updated as on | B14: 46217
A16: Scheme | B16: Suraksha Home Loan
A17: Loan type | B17: Term loan
C18: Floating rate
B20: Repo Rate | C20: Markup | D20: Final rate
B21: Rate base
A22: Occupation | B22: Salaried & Self-Employed
A23: 800+ | B23: ='Repo rate'!$B$4 -> 5.25 | C23: 2.15 | D23: =B23+C23 -> 7.4
A24: 750 - 799 | B24: ='Repo rate'!$B$4 -> 5.25 | C24: 2.4 | D24: =B24+C24 -> 7.65
A25: 700 - 749 | B25: ='Repo rate'!$B$4 -> 5.25 | C25: 3 | D25: =B25+C25 -> 8.25
A26: 650 - 699 | B26: ='Repo rate'!$B$4 -> 5.25 | C26: 3.2 | D26: =B26+C26 -> 8.45
A27: 600 - 649 | B27: ='Repo rate'!$B$4 -> 5.25 | C27: 3.6 | D27: =B27+C27 -> 8.85
A28: < 600 | B28: ='Repo rate'!$B$4 -> 5.25 | C28: 4 | D28: =B28+C28 -> 9.25

Sheet City Union Bank
A1: Bank | B1: City Union Bank
A2: Interest rate link | B2: https://cityunionbank.bank.in/eblr-interest-rate
A3: Credit score range given | B3: No
A4: Interest rates as per score | B4: No
A5: Gender split | B5: No
A6: Occupation split | B6: No
A7: Rate types | B7: Floating
A8: Rate base | B8: Repo + Mark-up
A9: Special Govt. Employees | B9: No
A10: Loan Type - Term Loan | B10: Yes
A11: Loan Type - Overdraft | B11: No
A12: Top up | B12: No
... A15: Occupation | B15: Salaried & Self-Employed
A16: Floating rate
A19: Scheme | B19: affordable Home Loan
A20: Loan type | B20: Term loan
D21: External Benchmark Lending Rate
B22: Repo Rate | C22: Markup | D22: rate base | E22: Discount | F22: Final rate
A23: Condition
A24: Loan amount | B24: upto 30 lakhs
A25: 800+ | B25: ='Repo rate'!$B$4 -> 5.25 | C25: 4.45 | D25: =B25+C25 -> 9.7 | E25: -1.45 | F25: =D25+E25 -> 8.25
A26: 700 -799 | B26: ='Repo rate'!$B$4 -> 5.25 | C26: 4.45 | D26: =B26+C26 -> 9.7 | E26: -1.2 | F26: =D26+E26 -> 8.5
A27: 100 - 200 | B27: ='Repo rate'!$B$4 -> 5.25 | C27: 4.45 | D27: =B27+C27 -> 9.7 | E27: -0.7 | F27: =D27+E27 -> 9
A29: Scheme | B29: Prime Home Loan
A30: Loan type | B30: Term loan
D32: External Benchmark Lending Rate
B33: Repo Rate | C33: Markup | D33: rate base | E33: Discount | F33: Final rate
A34: Condition
A35: Loan amount | B35: 30 lakhs to 75 lakhs
A36: 800+ | B36: ='Repo rate'!$B$4 -> 5.25 | C36: 4.45 | D36: =B36+C36 -> 9.7 | E36: -1.2 | F36: =D36+E36 -> 8.5
A37: 700 -799 | B37: ='Repo rate'!$B$4 -> 5.25 | C37: 4.45 | D37: =B37+C37 -> 9.7 | E37: -0.95 | F37: =D37+E37 -> 8.75
A38: 100 - 200 | B38: ='Repo rate'!$B$4 -> 5.25 | C38: 4.45 | D38: =B38+C38 -> 9.7 | E38: -0.45 | F38: =D38+E38 -> 9.25
A40: Scheme | B40: Premium Home Loan
A41: Loan type | B41: Term loan
A42: Floating rate
D43: External Benchmark Lending Rate
B44: Repo Rate | C44: Markup | D44: rate base | E44: Discount | F44: Final rate
A45: Condition
A46: Loan amount | B46: 75 lakhs to 7.5 crore
A47: 800+ | B47: ='Repo rate'!$B$4 -> 5.25 | C47: 4.45 | D47: =B47+C47 -> 9.7 | E47: -0.95 | F47: =D47+E47 -> 8.75
A48: 700 -799 | B48: ='Repo rate'!$B$4 -> 5.25 | C48: 4.45 | D48: =B48+C48 -> 9.7 | E48: -0.7 | F48: =D48+E48 -> 9
A49: 100 - 200 | B49: ='Repo rate'!$B$4 -> 5.25 | C49: 4.45 | D49: =B49+C49 -> 9.7 | E49: -0.2 | F49: =D49+E49 -> 9.5
A52: Occupation | B52: Salaried & Self-Employed
A53: term loan
A54: fixed rate
A56: Scheme | B56: affordable Home Loan
A57: Loan type | B57: Term loan | D57: External Benchmark Lending Rate
B58: Repo Rate | C58: Markup | D58: rate base | E58: Discount | F58: Final rate
A59: Condition
A60: Loan amount | B60: upto 30 lakhs
A61: 800+ | B61: ='Repo rate'!$B$4 -> 5.25 | C61: 4.45 | D61: =B61+C61 -> 9.7 | E61: -1.35 | F61: =D61+E61 -> 8.35
A62: 700 -799 | B62: ='Repo rate'!$B$4 -> 5.25 | C62: 4.45 | D62: =B62+C62 -> 9.7 | E62: -0.85 | F62: =D62+E62 -> 8.85
A63: 100 - 200 | B63: ='Repo rate'!$B$4 -> 5.25 | C63: 4.45 | D63: =B63+C63 -> 9.7 | E63: -0.35 | F63: =D63+E63 -> 9.35
A65: Scheme | B65: Prime Home Loan
A66: Loan type | B66: Term loan
D68: External Benchmark Lending Rate
B69: Repo Rate | C69: Markup | D69: rate base | E69: Discount | F69: Final rate
A70: Condition
A71: Loan amount | B71: 30 lakhs to 75 lakhs
A72: 800+ | B72: ='Repo rate'!$B$4 -> 5.25 | C72: 4.45 | D72: =B72+C72 -> 9.7 | E72: -0.85 | F72: =D72+E72 -> 8.85
A73: 700 -799 | B73: ='Repo rate'!$B$4 -> 5.25 | C73: 4.45 | D73: =B73+C73 -> 9.7 | E73: -0.35 | F73: =D73+E73 -> 9.35
A74: 100 - 200 | B74: ='Repo rate'!$B$4 -> 5.25 | C74: 4.45 | D74: =B74+C74 -> 9.7 | E74: 0.15 | F74: =D74+E74 -> 9.85
A76: Scheme | B76: Premium Home Loan
A77: Loan type | B77: Term loan
A78: Floating rate
D79: External Benchmark Lending Rate
B80: Repo Rate | C80: Markup | D80: rate base | E80: Discount | F80: Final rate
A81: Condition
A82: Loan amount | B82: 75 lakhs to 7.5 crore
A83: 800+ | B83: ='Repo rate'!$B$4 -> 5.25 | C83: 4.45 | D83: =B83+C83 -> 9.7 | E83: -0.35 | F83: =D83+E83 -> 9.35
A84: 700 -799 | B84: ='Repo rate'!$B$4 -> 5.25 | C84: 4.45 | D84: =B84+C84 -> 9.7 | E84: 0.15 | F84: =D84+E84 -> 9.85
A85: 100 - 200 | B85: ='Repo rate'!$B$4 -> 5.25 | C85: 4.45 | D85: =B85+C85 -> 9.7 | E85: 1.15 | F85: =D85+E85 -> 10.85

Sheet Axis Bank
A1: Bank | B1: Axis bank
A2: Interest rate link | B2: https://www.axis.bank.in/loans/home-loan/interest-rates-charges#interest-rates
A3: Credit score range given | B3: No
A4: Interest rates as per score | B4: No
A5: Gender split | B5: No
A6: Occupation split | B6: No
A7: Rate types | B7: Floating
A8: Rate base | B8: Repo
A9: Special Govt. Employees | B9: No
A10: Loan Type - Term Loan | B10: Yes
A11: Loan Type - Overdraft | B11: Yes
A12: Top up | B12: No
A13: Rate varies by insurance | B13: No
A14: Updated as on | B14: 46217
A16: Scheme | B16: Home Loan
A17: Loan type | B17: Term loan
A18: Floating rate
B20: Repo Rate | C20: Markup | D20: Final rate
B21: Rate base
A22: Occupation | B22: Salaried & Self-Employed
A23: 800+ | B23: ='Repo rate'!$B$4 -> 5.25 | C23: 1.95 | D23: =B23+C23 -> 7.2
A24: 750 - 799 | B24: ='Repo rate'!$B$4 -> 5.25 | C24: 2.1 | D24: =B24+C24 -> 7.35
A25: 700 - 749 | B25: ='Repo rate'!$B$4 -> 5.25 | C25: 2.35 | D25: =B25+C25 -> 7.6
A26: 650 - 699 | B26: ='Repo rate'!$B$4 -> 5.25 | C26: 2.75 | D26: =B26+C26 -> 8
A27: 600 - 649 | B27: ='Repo rate'!$B$4 -> 5.25 | C27: 3.45 | D27: =B27+C27 -> 8.7
A28: < 600 | B28: ='Repo rate'!$B$4 -> 5.25 | C28: 3.8 | D28: =B28+C28 -> 9.05
A31: Scheme | B31: Supre Saver Home Loan
A32: Loan type | B32: Overdraft
C33: Floating rate
A34: Occupation | B34: Salaried & Self-Employed
A35: 800+ | B35: ='Repo rate'!$B$4 -> 5.25 | C35: 2.35 | D35: =B35+C35 -> 7.6
A36: 750 - 799 | B36: ='Repo rate'!$B$4 -> 5.25 | C36: 2.5 | D36: =B36+C36 -> 7.75
A37: 700 - 749 | B37: ='Repo rate'!$B$4 -> 5.25 | C37: 2.85 | D37: =B37+C37 -> 8.1
A38: 650 - 699 | B38: ='Repo rate'!$B$4 -> 5.25 | C38: 3.15 | D38: =B38+C38 -> 8.4
A39: 600 - 649 | B39: ='Repo rate'!$B$4 -> 5.25 | C39: 3.85 | D39: =B39+C39 -> 9.1
A40: < 600 | B40: ='Repo rate'!$B$4 -> 5.25 | C40: 4.2 | D40: =B40+C40 -> 9.45

Sheet ICICI Bank
A1: Bank | B1: ICICI Bank
A2: Interest rate link | B2: https://www.icici.bank.in/personal-banking/loans/home-loan/interest-rates?ITM=nli_homeLoan_loans_homeLoan_na_3_na_na_NLI
A3: Credit score range given | B3: No
A4: Interest rates as per score | B4: No
A5: Gender split | B5: No
A6: Occupation split | B6: No
A7: Rate types | B7: Floating
A8: Rate base | B8: Repo
A9: Special Govt. Employees | B9: No
A10: Loan Type - Term Loan | B10: Yes
A11: Loan Type - Overdraft | B11: Yes
A12: Top up | B12: No
A13: Rate varies by insurance | B13: No
A14: Updated as on | B14: 46217
A17: Scheme | B17: Home Loan
A18: Loan type | B18: Term loan
A19: Floating rate
B21: Repo Rate | C21: Markup | D21: Final rate
B22: rate base
A23: Occupation | B23: Salaried & Self-Employed
A24: 800+ | B24: ='Repo rate'!$B$4 -> 5.25 | C24: 1.9 | D24: =B24+C24 -> 7.15
A25: 750 - 799 | B25: ='Repo rate'!$B$4 -> 5.25 | C25: 2.4 | D25: =B25+C25 -> 7.65
A26: 700 - 749 | B26: ='Repo rate'!$B$4 -> 5.25 | C26: 2.55 | D26: =B26+C26 -> 7.8
A27: 650 - 699 | B27: ='Repo rate'!$B$4 -> 5.25 | C27: 2.85 | D27: =B27+C27 -> 8.1
A28: 600 - 649 | B28: ='Repo rate'!$B$4 -> 5.25 | C28: 3.25 | D28: =B28+C28 -> 8.5
A29: < 600 | B29: ='Repo rate'!$B$4 -> 5.25 | C29: 3.55 | D29: =B29+C29 -> 8.8
A32: Scheme | B32: ICICI Money Saver
A33: Loan type | B33: Overdraft
A34: Floating rate
A36: Occupation | B36: Salaried & Self-Employed
A37: 800+ | B37: ='Repo rate'!$B$4 -> 5.25 | C37: 2.15 | D37: =B37+C37 -> 7.4
A38: 750 - 799 | B38: ='Repo rate'!$B$4 -> 5.25 | C38: 2.65 | D38: =B38+C38 -> 7.9
A39: 700 - 749 | B39: ='Repo rate'!$B$4 -> 5.25 | C39: 2.75 | D39: =B39+C39 -> 8
A40: 650 - 699 | B40: ='Repo rate'!$B$4 -> 5.25 | C40: 3.25 | D40: =B40+C40 -> 8.5
A41: 600 - 649 | B41: ='Repo rate'!$B$4 -> 5.25 | C41: 3.75 | D41: =B41+C41 -> 9
A42: < 600 | B42: ='Repo rate'!$B$4 -> 5.25 | C42: 3.95 | D42: =B42+C42 -> 9.2

Sheet HDFC Bank
A1: Bank | B1: HDFC Bank
A2: Interest rate link | B2: https://www.hdfc.bank.in/home-loan/interest-rates-and-charges
A3: Credit score range given | B3: No
A4: Interest rates as per score | B4: No
A5: Gender split | B5: No
A6: Occupation split | B6: No
A7: Rate types | B7: Floating
A8: Rate base | B8: Repo
A9: Special Govt. Employees | B9: No
A10: Loan Type - Term Loan | B10: Yes
A11: Loan Type - Overdraft | B11: Yes
A12: Top up | B12: No
A13: Rate varies by insurance | B13: No
A14: Updated as on | B14: 46217
A18: Scheme | B18: Home Loan
A19: Loan type | B19: Term loan
A20: Floating rate
B22: Repo Rate | C22: Markup | D22: Final rate
B23: rate base
A24: Occupation | B24: Salaried & Self-Employed
A25: 800+ | B25: ='Repo rate'!$B$4 -> 5.25 | C25: 2 | D25: =B25+C25 -> 7.25
A26: 750 - 799 | B26: ='Repo rate'!$B$4 -> 5.25 | C26: 2.35 | D26: =B26+C26 -> 7.6
A27: 700 - 749 | B27: ='Repo rate'!$B$4 -> 5.25 | C27: 2.65 | D27: =B27+C27 -> 7.9
A28: 650 - 699 | B28: ='Repo rate'!$B$4 -> 5.25 | C28: 2.9 | D28: =B28+C28 -> 8.15
A29: 600 - 649 | B29: ='Repo rate'!$B$4 -> 5.25 | C29: 3.2 | D29: =B29+C29 -> 8.45
A30: < 600 | B30: ='Repo rate'!$B$4 -> 5.25 | C30: 3.4 | D30: =B30+C30 -> 8.65

Sheet Dhanlaxmi Bank
A1: Bank | B1: Dhanlaxmi Bank
A2: Interest rate link | B2: https://www.dhan.bank.in/interest-rates/
A3: Credit score range given | B3: Yes | C3: Only internal rating is given.
A4: Interest rates as per score | B4: Yes
A5: Gender split | B5: No
A6: Occupation split | B6: No
A7: Rate types | B7: Floating
A8: Rate base | B8: Repo
A9: Special Govt. Employees | B9: No
A10: Loan Type - Term Loan | B10: Yes
A11: Loan Type - Overdraft | B11: Yes
A12: Top up | B12: No
A13: Rate varies by insurance | B13: No
A14: Updated as on | B14: 46217
A16: Scheme | B16: Home Loan
A17: Loan type | B17: Term loan
A18: Floating rate
B20: Internal Rating | C20: Repo Rate | D20: Markup | E20: Final rate
C21: rate base
A22: Occupation | B22: Salaried & Self-Employed
A23: 825+ | B23: AAA | C23: ='Repo rate'!$B$4 -> 5.25 | D23: 2.95 | E23: =C23+D23 -> 8.2
A24: 800 - 824 | B24: AAA | C24: ='Repo rate'!$B$4 -> 5.25 | D24: 3.05 | E24: =C24+D24 -> 8.3
A25: 750 - 799 | B25: AAA | C25: ='Repo rate'!$B$4 -> 5.25 | D25: 3.15 | E25: =C25+D25 -> 8.4
A26: 700 - 749 | B26: BBB | C26: ='Repo rate'!$B$4 -> 5.25 | D26: 3.75 | E26: =C26+D26 -> 9
A27: 650 - 699 | B27: BBB | C27: ='Repo rate'!$B$4 -> 5.25 | D27: 5.55 | E27: =C27+D27 -> 10.8
A28: 600 - 649 | B28: BBB | C28: ='Repo rate'!$B$4 -> 5.25 | D28: 5.75 | E28: =C28+D28 -> 11
A29: < 600 | B29: C | C29: ='Repo rate'!$B$4 -> 5.25 | D29: 6.25 | E29: =C29+D29 -> 11.5

Sheet Federal Bank
A1: Bank | B1: Federal Bank
A2: Interest rate link | B2: https://www.federal.bank.in/retail-loans-interest-rates
A3: Credit score range given | B3: No
A4: Interest rates as per score | B4: No
A5: Gender split | B5: No
A6: Occupation split | B6: No
A7: Rate types | B7: Floating
A8: Rate base | B8: Repo
A9: Special Govt. Employees | B9: No
A10: Loan Type - Term Loan | B10: Yes
A11: Loan Type - Overdraft | B11: No
A12: Top up | B12: No
A13: Rate varies by insurance | B13: No
A14: Updated as on | B14: 46217
A15: Scheme | B15: Home Loan
A16: Loan type | B16: Term loan
A17: Floating rate
B19: Repo Rate | C19: Markup | D19: Final rate
B20: rate base
A22: Occupation | B22: Salaried & Self-Employed
A23: 800+ | B23: ='Repo rate'!$B$4 -> 5.25 | C23: 2.1 | D23: =B23+C23 -> 7.35
A24: 750 - 799 | B24: ='Repo rate'!$B$4 -> 5.25 | C24: 2.5 | D24: =B24+C24 -> 7.75
A25: 700 - 749 | B25: ='Repo rate'!$B$4 -> 5.25 | C25: 2.7 | D25: =B25+C25 -> 7.95
A26: 650 - 699 | B26: ='Repo rate'!$B$4 -> 5.25 | C26: 3 | D26: =B26+C26 -> 8.25
A27: 600 - 649 | B27: ='Repo rate'!$B$4 -> 5.25 | C27: 3.4 | D27: =B27+C27 -> 8.65
A28: < 600 | B28: ='Repo rate'!$B$4 -> 5.25 | C28: 3.75 | D28: =B28+C28 -> 9

Sheet IDBI Bank
A1: Bank | B1: IDBI Bank
A2: Interest rate link | B2: https://www.idbi.bank.in/interest-rates.aspx
A3: Credit score range given | B3: Yes | D3: See the march pic in pixel
A4: Interest rates as per score | B4: Yes
A5: Gender split | B5: No
A6: Occupation split | B6: No
A7: Rate types | B7: Floating
A8: Rate base | B8: Repo + Mark-up
A9: Special Govt. Employees | B9: No
A10: Loan Type - Term Loan | B10: Yes
A11: Loan Type - Overdraft | B11: Yes
A12: Top up | B12: No
A13: Rate varies by insurance | B13: No
A14: Updated as on | B14: 46217
A16: Scheme | B16: Plain Vanilla Home Loan
A17: Loan type | B17: Term loan
A18: Floating rate
B20: Repo Rate | C20: Markup | D20: RLLR | E20: Discount | F20: Final rate
A22: Occupation | B22: Salaried & Self-Employed
A23: 825+ | B23: ='Repo rate'!$B$4 -> 5.25 | C23: 2.9 | D23: =B23+C23 -> 8.15 | E23: -0.8 | F23: =D23+E23 -> 7.35
A24: 781 - 824 | B24: ='Repo rate'!$B$4 -> 5.25 | C24: 2.9 | D24: =B24+C24 -> 8.15 | E24: -0.45 | F24: =D24+E24 -> 7.7
A25: 761 - 780 | B25: ='Repo rate'!$B$4 -> 5.25 | C25: 2.9 | D25: =B25+C25 -> 8.15 | E25: -0.2 | F25: =D25+E25 -> 7.95
A26: 741 - 760 | B26: ='Repo rate'!$B$4 -> 5.25 | C26: 2.9 | D26: =B26+C26 -> 8.15 | E26: -0.1 | F26: =D26+E26 -> 8.05
A27: 721 - 740 | B27: ='Repo rate'!$B$4 -> 5.25 | C27: 2.9 | D27: =B27+C27 -> 8.15 | E27: 0.75 | F27: =D27+E27 -> 8.9
A28: 700 - 720 | B28: ='Repo rate'!$B$4 -> 5.25 | C28: 2.9 | D28: =B28+C28 -> 8.15 | E28: 1.3 | F28: =D28+E28 -> 9.45
A29: 650 - 699 | B29: ='Repo rate'!$B$4 -> 5.25 | C29: 2.9 | D29: =B29+C29 -> 8.15 | E29: 1.9 | F29: =D29+E29 -> 10.05
A31: Scheme | B31: Home Loan Ultra Saver
A32: Loan type | B32: Overdraft
A35: Occupation | B35: Salaried & Self-Employed
A36: 825+ | B36: ='Repo rate'!$B$4 -> 5.25 | C36: 2.9 | D36: =B36+C36 -> 8.15 | E36: -0.4 | F36: =D36+E36 -> 7.75
A37: 781 - 824 | B37: ='Repo rate'!$B$4 -> 5.25 | C37: 2.9 | D37: =B37+C37 -> 8.15 | E37: -0.05 | F37: =D37+E37 -> 8.1
A38: 761 - 780 | B38: ='Repo rate'!$B$4 -> 5.25 | C38: 2.9 | D38: =B38+C38 -> 8.15 | E38: 0.2 | F38: =D38+E38 -> 8.35
A39: 741 - 760 | B39: ='Repo rate'!$B$4 -> 5.25 | C39: 2.9 | D39: =B39+C39 -> 8.15 | E39: 0.3 | F39: =D39+E39 -> 8.45
A40: 721 - 740 | B40: ='Repo rate'!$B$4 -> 5.25 | C40: 2.9 | D40: =B40+C40 -> 8.15 | E40: 1.15 | F40: =D40+E40 -> 9.3
A41: 700 - 720 | B41: ='Repo rate'!$B$4 -> 5.25 | C41: 2.9 | D41: =B41+C41 -> 8.15 | E41: 1.7 | F41: =D41+E41 -> 9.85
A42: 650 - 699 | B42: ='Repo rate'!$B$4 -> 5.25 | C42: 2.9 | D42: =B42+C42 -> 8.15 | E42: 2.3 | F42: =D42+E42 -> 10.45
A45: Scheme | B45: Home loan Top Up
A46: Loan type | B46: Term loan
A49: Occupation | B49: Salaried & Self-Employed
A50: 825+ | B50: ='Repo rate'!$B$4 -> 5.25 | C50: 2.9 | D50: =B50+C50 -> 8.15 | E50: -0.6 | F50: =D50+E50 -> 7.55
A51: 781 - 824 | B51: ='Repo rate'!$B$4 -> 5.25 | C51: 2.9 | D51: =B51+C51 -> 8.15 | E51: -0.25 | F51: =D51+E51 -> 7.9
A52: 761 - 780 | B52: ='Repo rate'!$B$4 -> 5.25 | C52: 2.9 | D52: =B52+C52 -> 8.15 | E52: 0 | F52: =D52+E52 -> 8.15
A53: 741 - 760 | B53: ='Repo rate'!$B$4 -> 5.25 | C53: 2.9 | D53: =B53+C53 -> 8.15 | E53: 0.1 | F53: =D53+E53 -> 8.25
A54: 721 - 740 | B54: ='Repo rate'!$B$4 -> 5.25 | C54: 2.9 | D54: =B54+C54 -> 8.15 | E54: 0.95 | F54: =D54+E54 -> 9.1
A55: 700 - 720 | B55: ='Repo rate'!$B$4 -> 5.25 | C55: 2.9 | D55: =B55+C55 -> 8.15 | E55: 1.5 | F55: =D55+E55 -> 9.65
A56: 650 - 699 | B56: ='Repo rate'!$B$4 -> 5.25 | C56: 2.9 | D56: =B56+C56 -> 8.15 | E56: 2.1 | F56: =D56+E56 -> 10.25

Sheet IDFC First Bank
A1: Bank | B1: IDFC First Bank
A2: Interest rate link | B2: https://www.idfcfirst.bank.in/personal-banking/loans/home-loan/fees-and-charges
A3: Credit score range given | B3: No
A4: Interest rates as per score | B4: No
A5: Gender split | B5: No
A6: Occupation split | B6: No
A7: Rate types | B7: Floating
A8: Rate base | B8: Repo + Mark-up
A9: Special Govt. Employees | B9: No
A10: Loan Type - Term Loan | B10: Yes
A11: Loan Type - Overdraft | B11: No
A12: Top up | B12: No
A13: Rate varies by insurance | B13: No
A14: Updated as on | B14: 46217
A15: Scheme | B15: Home Loan
A16: Loan type | B16: Term loan
A17: Floating rate
D18: RLLR
B19: Repo Rate | C19: Markup | D19: rate base | E19: Discount | F19: Final rate
A21: Occupation | B21: Salaried & Self-Employed
A22: 800 + | B22: ='Repo rate'!$B$4 -> 5.25 | C22: 2 | D22: =B22+C22 -> 7.25 | E22: 0.5 | F22: =D22+E22 -> 7.75
A23: 750 - 799 | B23: ='Repo rate'!$B$4 -> 5.25 | C23: 2 | D23: =B23+C23 -> 7.25 | E23: 0.7 | F23: =D23+E23 -> 7.95
A24: 700 - 749 | B24: ='Repo rate'!$B$4 -> 5.25 | C24: 2 | D24: =B24+C24 -> 7.25 | E24: 0.9 | F24: =D24+E24 -> 8.15
A25: 650 - 699 | B25: ='Repo rate'!$B$4 -> 5.25 | C25: 2 | D25: =B25+C25 -> 7.25 | E25: 1.2 | F25: =D25+E25 -> 8.45
A26: 600 - 649 | B26: ='Repo rate'!$B$4 -> 5.25 | C26: 2 | D26: =B26+C26 -> 7.25 | E26: 1.35 | F26: =D26+E26 -> 8.6

Sheet Karur Vyasa Bank
A1: Bank | B1: Karur Vyasa Bank
A2: Interest rate link | B2: https://www.kvb.bank.in/interest-rates/
A3: Credit score range given | B3: No
A4: Interest rates as per score | B4: No
A5: Gender split | B5: No
A6: Occupation split | B6: No
A7: Rate types | B7: Floating
A8: Rate base | B8: Repo + Mark-up
A9: Special Govt. Employees | B9: No
A10: Loan Type - Term Loan | B10: Yes
A11: Loan Type - Overdraft | B11: No
A12: Top up | B12: No
A13: Rate varies by insurance | B13: No
A14: Updated as on | B14: 46217
A15: Scheme | B15: Housing Loan
A16: Loan type | B16: Term loan
A17: Floating rate
D18: RLLR
B19: Repo Rate | C19: Markup | D19: rate base | E19: Discount | F19: Final rate
A21: Occupation | B21: Salaried & Self-Employed
A22: 800 + | B22: ='Repo rate'!$B$4 -> 5.25 | C22: 3.3 | D22: =B22+C22 -> 8.55 | E22: -0.05 | F22: =D22+E22 -> 8.5
A23: 750 - 799 | B23: ='Repo rate'!$B$4 -> 5.25 | C23: 3.3 | D23: =B23+C23 -> 8.55 | E23: 0.2 | F23: =D23+E23 -> 8.75
A24: 700 - 749 | B24: ='Repo rate'!$B$4 -> 5.25 | C24: 3.3 | D24: =B24+C24 -> 8.55 | E24: 0.8 | F24: =D24+E24 -> 9.35
A25: 650 - 699 | B25: ='Repo rate'!$B$4 -> 5.25 | C25: 3.3 | D25: =B25+C25 -> 8.55 | E25: 1.6 | F25: =D25+E25 -> 10.15
A26: 600 - 649 | B26: ='Repo rate'!$B$4 -> 5.25 | C26: 3.3 | D26: =B26+C26 -> 8.55 | E26: 2.1 | F26: =D26+E26 -> 10.65
A28: Scheme | B28: Housing Loan Topup
A29: Loan type | B29: Term loan
A30: Floating rate
A32: Occupation | B32: Salaried & Self-Employed
A33: 800 + | B33: ='Repo rate'!$B$4 -> 5.25 | C33: 3.3 | D33: =B33+C33 -> 8.55 | E33: 0.2 | F33: =D33+E33 -> 8.75
A34: 750 - 799 | B34: ='Repo rate'!$B$4 -> 5.25 | C34: 3.3 | D34: =B34+C34 -> 8.55 | E34: 0.5 | F34: =D34+E34 -> 9.05
A35: 700 - 749 | B35: ='Repo rate'!$B$4 -> 5.25 | C35: 3.3 | D35: =B35+C35 -> 8.55 | E35: 1 | F35: =D35+E35 -> 9.55
A36: 650 - 699 | B36: ='Repo rate'!$B$4 -> 5.25 | C36: 3.3 | D36: =B36+C36 -> 8.55 | E36: 1.4 | F36: =D36+E36 -> 9.95
A37: 600 - 649 | B37: ='Repo rate'!$B$4 -> 5.25 | C37: 3.3 | D37: =B37+C37 -> 8.55 | E37: 1.7 | F37: =D37+E37 -> 10.25

Sheet Kotak Mahindra Bank
A1: Bank | B1: Kotak Mahindra Bank
A2: Interest rate link | B2: https://www.kotak.bank.in/en/personal-banking/loans/home-loan/interest-rates.html
A3: Credit score range given | B3: No
A4: Interest rates as per score | B4: No
A5: Gender split | B5: No
A6: Occupation split | B6: No
A7: Rate types | B7: Floating
A8: Rate base | B8: Repo
A9: Special Govt. Employees | B9: No
A10: Loan Type - Term Loan | B10: Yes
A11: Loan Type - Overdraft | B11: No
A12: Top up | B12: No
A13: Rate varies by insurance | B13: No
A14: Updated as on | B14: 46217
A15: Scheme | B15: Home Loan
A16: Loan type | B16: Term loan
A17: Floating rate
B19: Repo Rate | C19: Markup | D19: Final rate
B20: rate base
A21: Occupation | B21: Salaried & Self-Employed
A22: 800+ | B22: ='Repo rate'!$B$4 -> 5.25 | C22: 2.35 | D22: =B22+C22 -> 7.6
A23: 750 - 799 | B23: ='Repo rate'!$B$4 -> 5.25 | C23: 2.6 | D23: =B23+C23 -> 7.85
A24: 700 - 749 | B24: ='Repo rate'!$B$4 -> 5.25 | C24: 2.9 | D24: =B24+C24 -> 8.15
A25: 650 - 699 | B25: ='Repo rate'!$B$4 -> 5.25 | C25: 3.1 | D25: =B25+C25 -> 8.35
A26: 600 - 649 | B26: ='Repo rate'!$B$4 -> 5.25 | C26: 3.4 | D26: =B26+C26 -> 8.65
A27: < 600 | B27: ='Repo rate'!$B$4 -> 5.25 | C27: 3.6 | D27: =B27+C27 -> 8.85

Sheet Karnataka Bank
A1: Bank | B1: Karnataka Bank
A2: Interest rate link | B2: https://www.karnatakabank.bank.in/loan-interest-rates
A3: Credit score range given | B3: No
A4: Interest rates as per score | B4: No
A5: Gender split | B5: No
A6: Occupation split | B6: No
A7: Rate types | B7: Floating
A8: Rate base | B8: Repo
A9: Special Govt. Employees | B9: No
A10: Loan Type - Term Loan | B10: Yes
A11: Loan Type - Overdraft | B11: No
A12: Top up | B12: No
A13: Rate varies by insurance | B13: No
A14: Updated as on | B14: 46249
A15: Scheme | B15: KBL - Apna Ghar
A16: Loan type | B16: Term loan
A17: Floating rate
B19: Repo Rate | C19: Markup | D19: Final rate
B20: rate base
A21: Occupation | B21: Salaried & Self-Employed
A22: 800+ | B22: ='Repo rate'!$B$4 -> 5.25 | C22: 2.23 | D22: =B22+C22 -> 7.48
A23: 750 - 799 | B23: ='Repo rate'!$B$4 -> 5.25 | C23: 3 | D23: =B23+C23 -> 8.25
A24: 700 - 749 | B24: ='Repo rate'!$B$4 -> 5.25 | C24: 3.5 | D24: =B24+C24 -> 8.75
A25: 650 - 699 | B25: ='Repo rate'!$B$4 -> 5.25 | C25: 4.2 | D25: =B25+C25 -> 9.45
A26: 600 - 649 | B26: ='Repo rate'!$B$4 -> 5.25 | C26: 5.5 | D26: =B26+C26 -> 10.75
A27: < 600 | B27: ='Repo rate'!$B$4 -> 5.25 | C27: 6.55 | D27: =B27+C27 -> 11.8

Sheet RBL Bank
A1: Bank | B1: RBL Bank
A2: Interest rate link | B2: https://www.rbl.bank.in/personal-banking/loans/housing-loan?tabName=why-us
A3: Credit score range given | B3: No
A4: Interest rates as per score | B4: No
A5: Gender split | B5: No
A6: Occupation split | B6: No
A7: Rate types | B7: Floating
A8: Rate base | B8: Repo
A9: Special Govt. Employees | B9: No
A10: Loan Type - Term Loan | B10: Yes
A11: Loan Type - Overdraft | B11: No
A12: Top up | B12: No
A13: Rate varies by insurance | B13: No
A14: Updated as on | B14: 46217
A15: Scheme | B15: Housing Loan
A16: Loan type | B16: Term loan
A17: Floating rate
B19: Repo Rate | C19: Markup | D19: Final rate
B20: rate base
A21: Occupation | B21: Salaried & Self-Employed
A22: 800+ | B22: ='Repo rate'!$B$4 -> 5.25 | C22: 3.75 | D22: =B22+C22 -> 9
A23: 750 - 799 | B23: ='Repo rate'!$B$4 -> 5.25 | C23: 4.1 | D23: =B23+C23 -> 9.35
A24: 700 - 749 | B24: ='Repo rate'!$B$4 -> 5.25 | C24: 4.5 | D24: =B24+C24 -> 9.75
A25: 650 - 699 | B25: ='Repo rate'!$B$4 -> 5.25 | C25: 5 | D25: =B25+C25 -> 10.25
A26: 600 - 649 | B26: ='Repo rate'!$B$4 -> 5.25 | C26: 5.4 | D26: =B26+C26 -> 10.65
A27: < 600 | B27: ='Repo rate'!$B$4 -> 5.25 | C27: 6 | D27: =B27+C27 -> 11.25

Sheet South Indian Bank
A1: Bank | B1: South Indian Bank
A2: Interest rate link | B2: https://www.southindianbank.bank.in/quick-links/interest-rates/loans
A3: Credit score range given | B3: No
A4: Interest rates as per score | B4: No
A5: Gender split | B5: No
A6: Occupation split | B6: No
A7: Rate types | B7: Floating
A8: Rate base | B8: Repo
A9: Special Govt. Employees | B9: No
A10: Loan Type - Term Loan | B10: Yes
A11: Loan Type - Overdraft | B11: No
A12: Top up | B12: No
A13: Rate varies by insurance | B13: No
A14: Updated as on | B14: 46249
A15: Scheme | B15: SIB Home Loan
A16: Loan type | B16: Term loan
A17: Floating rate
B19: Repo Rate | C19: Markup | D19: Final rate
B20: rate base
A21: Occupation | B21: Salaried & Self-Employed
A22: 800+ | B22: ='Repo rate'!$B$4 -> 5.25 | C22: 2 | D22: =B22+C22 -> 7.25
A23: 750 - 799 | B23: ='Repo rate'!$B$4 -> 5.25 | C23: 2.2 | D23: =B23+C23 -> 7.45
A24: 700 - 749 | B24: ='Repo rate'!$B$4 -> 5.25 | C24: 2.5 | D24: =B24+C24 -> 7.75
A25: 650 - 699 | B25: ='Repo rate'!$B$4 -> 5.25 | C25: 2.8 | D25: =B25+C25 -> 8.05
A26: 600 - 649 | B26: ='Repo rate'!$B$4 -> 5.25 | C26: 3.15 | D26: =B26+C26 -> 8.4
A27: < 600 | B27: ='Repo rate'!$B$4 -> 5.25 | C27: 3.4 | D27: =B27+C27 -> 8.65

Sheet Nainital Bank
A1: Bank | B1: Nainital Bank
A2: Interest rate link | B2: https://www.nainitalbank.bank.in/english/interest_rate.aspx
A3: Credit score range given | B3: Yes
A4: Interest rates as per score | B4: Yes
A5: Gender split | B5: No
A6: Occupation split | B6: No
A7: Rate types | B7: Floating
A8: Rate base | B8: Repo + Mark-up
A9: Special Govt. Employees | B9: Yes
A10: Loan Type - Term Loan | B10: Yes
A11: Loan Type - Overdraft | B11: No
A12: Top up | B12: Yes
A13: Rate varies by insurance | B13: Yes
A14: Updated as on | B14: 46217
A16: Scheme | B16: Apna Aashiana - Home loan
A17: Loan type | B17: Term loan
A18: Floating rate
B20: Repo Rate | C20: Markup | D20: Naini Repo Linked Lending Rate | E20: Discount | F20: Final rate | G20: Remarks
D21: rate base
A22: Occupation | B22: Salaried & Self-Employed
A23: 800+ | B23: ='Repo rate'!$B$4 -> 5.25 | C23: 3 | D23: =B23+C23 -> 8.25 | E23: -1.05 | F23: =D23+E23 -> 7.2 | G23: Govt, emplopyee
A24: 800+ | B24: ='Repo rate'!$B$4 -> 5.25 | C24: 3 | D24: =B24+C24 -> 8.25 | E24: -0.95 | F24: =D24+E24 -> 7.3 | G24: Others
A25: 750 - 799 | B25: ='Repo rate'!$B$4 -> 5.25 | C25: 3 | D25: =B25+C25 -> 8.25 | E25: -0.75 | F25: =D25+E25 -> 7.5
A26: 701 - 749 | B26: ='Repo rate'!$B$4 -> 5.25 | C26: 3 | D26: =B26+C26 -> 8.25 | E26: -0.4 | F26: =D26+E26 -> 7.85
A27: 675 - 700 | B27: ='Repo rate'!$B$4 -> 5.25 | C27: 3 | D27: =B27+C27 -> 8.25 | E27: 0.25 | F27: =D27+E27 -> 8.5
A28: 650 - 674 | B28: ='Repo rate'!$B$4 -> 5.25 | C28: 3 | D28: =B28+C28 -> 8.25 | E28: 0.65 | F28: =D28+E28 -> 8.9
A29: < 650 | B29: ='Repo rate'!$B$4 -> 5.25 | C29: 3 | D29: =B29+C29 -> 8.25 | E29: 1.8 | F29: =D29+E29 -> 10.05
A30: NTC | B30: ='Repo rate'!$B$4 -> 5.25 | C30: 3 | D30: =B30+C30 -> 8.25 | E30: -0.4 | F30: =D30+E30 -> 7.85
A33: Scheme | B33: Apna Aashiana - Top up Home loan
A34: Loan type | B34: Term loan
A35: Floating rate
B37: Repo Rate | C37: Markup | D37: Naini Repo Linked Lending Rate | E37: Discount | F37: Final rate | G37: Remarks
A39: Occupation | B39: Salaried & Self-Employed
A40: 800+ | B40: ='Repo rate'!$B$4 -> 5.25 | C40: 3 | D40: =B40+C40 -> 8.25 | E40: 0.85 | F40: =D40+E40 -> 9.1 | G40: Govt, emplopyee
A41: 800+ | B41: ='Repo rate'!$B$4 -> 5.25 | C41: 3 | D41: =B41+C41 -> 8.25 | E41: 0.95 | F41: =D41+E41 -> 9.2
A42: 750 - 799 | B42: ='Repo rate'!$B$4 -> 5.25 | C42: 3 | D42: =B42+C42 -> 8.25 | E42: 1.15 | F42: =D42+E42 -> 9.4
A43: 701 - 749 | B43: ='Repo rate'!$B$4 -> 5.25 | C43: 3 | D43: =B43+C43 -> 8.25 | E43: 1.5 | F43: =D43+E43 -> 9.75
A44: 675 - 700 | B44: ='Repo rate'!$B$4 -> 5.25 | C44: 3 | D44: =B44+C44 -> 8.25 | E44: 2.15 | F44: =D44+E44 -> 10.4
A45: 650 - 674 | B45: ='Repo rate'!$B$4 -> 5.25 | C45: 3 | D45: =B45+C45 -> 8.25 | E45: 2.55 | F45: =D45+E45 -> 10.8
A46: < 650 | B46: ='Repo rate'!$B$4 -> 5.25 | C46: 3 | D46: =B46+C46 -> 8.25 | E46: 3.7 | F46: =D46+E46 -> 11.95
A47: NTC | B47: ='Repo rate'!$B$4 -> 5.25 | C47: 3 | D47: =B47+C47 -> 8.25 | E47: 1.5 | F47: =D47+E47 -> 9.75
A50: Notes for | B50: Apna Aashiana - Home loan
A51: 0.05 insurance concession

Sheet Yes Bank
A1: Bank | B1: Yes Bank
A2: Interest rate link | B2: https://www.yes.bank.in/personal-banking/yes-individual/loans/home-loan
A3: Credit score range given | B3: No
A4: Interest rates as per score | B4: No
A5: Gender split | B5: No
A6: Occupation split | B6: No
A7: Rate types | B7: Floating
A8: Rate base | B8: Repo
A9: Special Govt. Employees | B9: No
A10: Loan Type - Term Loan | B10: Yes
A11: Loan Type - Overdraft | B11: No
A12: Top up | B12: No
A13: Rate varies by insurance | B13: No
A14: Updated as on | B14: 46217
A16: Scheme | B16: Home Loan
A17: Loan type | B17: Term loan
A18: Floating rate
B20: Repo Rate | C20: Markup | D20: Final rate
B21: rate base
A22: Occupation | B22: Salaried & Self-Employed
A23: 800+ | B23: ='Repo rate'!$B$4 -> 5.25 | C23: 3.4 | D23: =B23+C23 -> 8.65
A24: 750 - 799 | B24: ='Repo rate'!$B$4 -> 5.25 | C24: 3.6 | D24: =B24+C24 -> 8.85
A25: 700 - 749 | B25: ='Repo rate'!$B$4 -> 5.25 | C25: 3.95 | D25: =B25+C25 -> 9.2
A26: 650 - 699 | B26: ='Repo rate'!$B$4 -> 5.25 | C26: 4.15 | D26: =B26+C26 -> 9.4
A27: 600 - 649 | B27: ='Repo rate'!$B$4 -> 5.25 | C27: 4.4 | D27: =B27+C27 -> 9.65
A28: < 600 | B28: ='Repo rate'!$B$4 -> 5.25 | C28: 4.8 | D28: =B28+C28 -> 10.05

Sheet CSB Bank
A1: Bank | B1: CSB Bank
A2: Interest rate link | B2: https://www.csb.bank.in/housing-loan
A3: Credit score range given | B3: No
A4: Interest rates as per score | B4: No
A5: Gender split | B5: No
A6: Occupation split | B6: No
A7: Rate types | B7: Floating
A8: Rate base | B8: Repo
A9: Special Govt. Employees | B9: No
A10: Loan Type - Term Loan | B10: Yes
A11: Loan Type - Overdraft | B11: No
A12: Top up | B12: No
A13: Rate varies by insurance | B13: No
A14: Updated as on | B14: 46217
A16: Scheme | B16: Housing Loan
A17: Loan type | B17: Term loan
A18: Floating rate
B20: Repo Rate | C20: Markup | D20: Final rate
B21: rate base
A22: Occupation | B22: Salaried & Self-Employed
A23: 800+ | B23: ='Repo rate'!$B$4 -> 5.25 | C23: 3.05 | D23: =B23+C23 -> 8.3
A24: 750 - 799 | B24: ='Repo rate'!$B$4 -> 5.25 | C24: 3.4 | D24: =B24+C24 -> 8.65
A25: 700 - 749 | B25: ='Repo rate'!$B$4 -> 5.25 | C25: 3.8 | D25: =B25+C25 -> 9.05
A26: 650 - 699 | B26: ='Repo rate'!$B$4 -> 5.25 | C26: 4.2 | D26: =B26+C26 -> 9.45
A27: 600 - 649 | B27: ='Repo rate'!$B$4 -> 5.25 | C27: 4.6 | D27: =B27+C27 -> 9.85
A28: < 600 | B28: ='Repo rate'!$B$4 -> 5.25 | C28: 4.9 | D28: =B28+C28 -> 10.15

Sheet Tamilnad Mercantile Bank
A1: Bank | B1: Tamilnad Mercantile Bank
A2: Interest rate link | B2: https://www.tmb.bank.in/personal/loans/tmb-home-loan
A3: Credit score range given | B3: No
A4: Interest rates as per score | B4: No
A5: Gender split | B5: No
A6: Occupation split | B6: No
A7: Rate types | B7: Floating
A8: Rate base | B8: Repo + Mark-up
A9: Special Govt. Employees | B9: No
A10: Loan Type - Term Loan | B10: Yes
A11: Loan Type - Overdraft | B11: No
A12: Top up | B12: No
A13: Rate varies by insurance | B13: No
A14: Updated as on | B14: 46217
A15: Scheme | B15: Elite Home Loan
A16: Loan type | B16: Term loan
A17: Floating rate
B19: Repo Rate | C19: Markup | D19: Repo Linked Lending Rate | E19: Discount | F19: Final rate
D20: rate base
A21: Occupation | B21: Salaried & Self-Employed
A22: 800+ | B22: ='Repo rate'!$B$4 -> 5.25 | C22: 3 | D22: =B22+C22 -> 8.25 | E22: -0.35 | F22: =D22+E22 -> 7.9
A23: 750 - 799 | B23: ='Repo rate'!$B$4 -> 5.25 | C23: 3 | D23: =B23+C23 -> 8.25 | E23: -0.1 | F23: =D23+E23 -> 8.15
A24: 701 - 749 | B24: ='Repo rate'!$B$4 -> 5.25 | C24: 3 | D24: =B24+C24 -> 8.25 | E24: 0.5 | F24: =D24+E24 -> 8.75
A25: 675 - 700 | B25: ='Repo rate'!$B$4 -> 5.25 | C25: 3 | D25: =B25+C25 -> 8.25 | E25: 0.75 | F25: =D25+E25 -> 9
A26: 650 - 674 | B26: ='Repo rate'!$B$4 -> 5.25 | C26: 3 | D26: =B26+C26 -> 8.25 | E26: 0.95 | F26: =D26+E26 -> 9.2
A27: < 650 | B27: ='Repo rate'!$B$4 -> 5.25 | C27: 3 | D27: =B27+C27 -> 8.25 | E27: 1.5 | F27: =D27+E27 -> 9.75
A28: NTC | B28: ='Repo rate'!$B$4 -> 5.25 | C28: 3 | D28: =B28+C28 -> 8.25 | E28: 0.2 | F28: =D28+E28 -> 8.45

Sheet Indusind Bank
A1: Bank | B1: Indusind Bank
A2: Interest rate link | B2: https://www.indusind.bank.in/in/en/personal/other/know-more-about-APR-data.html
A3: Credit score range given | B3: No
A4: Interest rates as per score | B4: No
A5: Gender split | B5: No
A6: Occupation split | B6: No
A7: Rate types | B7: Floating
A8: Rate base | B8: Repo
A9: Special Govt. Employees | B9: No
A10: Loan Type - Term Loan | B10: Yes
A11: Loan Type - Overdraft | B11: No
A12: Top up | B12: No
A13: Rate varies by insurance | B13: No
A14: Updated as on | B14: 46249
A15: Scheme | B15: Home Loan
A16: Loan type | B16: Term loan
A17: Floating rate
B19: Repo Rate | C19: Discount | D19: Final rate
B20: rate base
A21: Occupation | B21: Salaried & Self-Employed
A22: 800+ | B22: ='Repo rate'!$B$4 -> 5.25 | C22: 2.35 | D22: =B22+C22 -> 7.6
A23: 750 - 799 | B23: ='Repo rate'!$B$4 -> 5.25 | C23: 2.5 | D23: =B23+C23 -> 7.75
A24: 701 - 749 | B24: ='Repo rate'!$B$4 -> 5.25 | C24: 2.85 | D24: =B24+C24 -> 8.1
A25: 675 - 700 | B25: ='Repo rate'!$B$4 -> 5.25 | C25: 3.05 | D25: =B25+C25 -> 8.3
A26: 650 - 674 | B26: ='Repo rate'!$B$4 -> 5.25 | C26: 3.7 | D26: =B26+C26 -> 8.95
A27: < 650 | B27: ='Repo rate'!$B$4 -> 5.25 | C27: 4.2 | D27: =B27+C27 -> 9.45
A28: NTC | B28: ='Repo rate'!$B$4 -> 5.25 | C28: 4.75 | D28: =B28+C28 -> 10

Sheet LIC Housing Finance
A1: Bank | B1: LIC Housing Finance
A2: Interest rate link | B2: https://www.pnbhousing.com/home-loan/interest-rates
A3: Credit score range given | B3: Yes
A4: Interest rates as per score | B4: Yes
A5: Gender split | B5: No
A6: Occupation split | B6: Yes
A7: Rate types | B7: Floating
A8: Rate base | B8: Published rate (CIBIL & loan slab linked)
A9: Special Govt. Employees | B9: No
A10: Loan Type - Term Loan | B10: Yes
A11: Loan Type - Overdraft | B11: No
A12: Top up | B12: No
A13: Rate varies by insurance | B13: No
A14: LIC Housing Prime Lending Rate | B14: 16.9
A16: Occupation | B16: Salaried
A17: Scheme | B17: Home Loan
A18: Loan type | B18: Term loan
A19: Floating rate
B20: LIC Housing Prime Lending Rate | C20: Markup | D20: Rate base | E20: Discount / Extra | F20: Final rate
A21: Condition
A22: Loan amount | B22: Up to 5 crs
A23: CIBIL ≥ 825 | B23: =B14 -> 16.9 | D23: =B23+C23 -> 16.9 | E23: -9.75 | F23: =D23+E23 -> 7.15
A24: CIBIL 800-824 | B24: =$B$14 -> 16.9 | D24: =B24+C24 -> 16.9 | E24: -9.65 | F24: =D24+E24 -> 7.25
A26: Condition
A27: Loan amount | B27: More than 5 crs & up to 15 crs
A28: CIBIL ≥ 825 | B28: =$B$14 -> 16.9 | D28: =B28+C28 -> 16.9 | E28: -9.45 | F28: =D28+E28 -> 7.45
A29: CIBIL 800-824 | B29: =$B$14 -> 16.9 | D29: =B29+C29 -> 16.9 | E29: -9.35 | F29: =D29+E29 -> 7.55
A31: Condition
A32: Loan amount | B32: Up to 50 lakhs
A33: CIBIL 775-799 | B33: =$B$14 -> 16.9 | D33: =B33+C33 -> 16.9 | E33: -9.55 | F33: =D33+E33 -> 7.35
A34: CIBIL 750-774 | B34: =$B$14 -> 16.9 | D34: =B34+C34 -> 16.9 | E34: -9.45 | F34: =D34+E34 -> 7.45
A35: CIBIL 725-749 | B35: =$B$14 -> 16.9 | D35: =B35+C35 -> 16.9 | E35: -9.25 | F35: =D35+E35 -> 7.65
A36: CIBIL 700-724 | B36: =$B$14 -> 16.9 | D36: =B36+C36 -> 16.9 | E36: -8.95 | F36: =D36+E36 -> 7.95
A37: CIBIL 600-699 | B37: =$B$14 -> 16.9 | D37: =B37+C37 -> 16.9 | E37: -8.15 | F37: =D37+E37 -> 8.75
A38: CIBIL <600 | B38: =$B$14 -> 16.9 | D38: =B38+C38 -> 16.9 | E38: -7.35 | F38: =D38+E38 -> 9.55
A40: Condition
A41: Loan amount | B41: More than 50 lakhs & up to 2 crs
A42: CIBIL 775-799 | B42: =$B$14 -> 16.9 | D42: =B42+C42 -> 16.9 | E42: -9.45 | F42: =D42+E42 -> 7.45
A43: CIBIL 750-774 | B43: =$B$14 -> 16.9 | D43: =B43+C43 -> 16.9 | E43: -9.35 | F43: =D43+E43 -> 7.55
A44: CIBIL 725-749 | B44: =$B$14 -> 16.9 | D44: =B44+C44 -> 16.9 | E44: -9.15 | F44: =D44+E44 -> 7.75
A45: CIBIL 700-724 | B45: =$B$14 -> 16.9 | D45: =B45+C45 -> 16.9 | E45: -8.85 | F45: =D45+E45 -> 8.05
A46: CIBIL 600-699 | B46: =$B$14 -> 16.9 | D46: =B46+C46 -> 16.9 | E46: -8.05 | F46: =D46+E46 -> 8.85
A47: CIBIL <600 | B47: =$B$14 -> 16.9 | D47: =B47+C47 -> 16.9 | E47: -7.25 | F47: =D47+E47 -> 9.65
A49: Condition
A50: Loan amount | B50: More than 2 crs & up to 15 crs
A51: CIBIL 775-799 | B51: =$B$14 -> 16.9 | D51: =B51+C51 -> 16.9 | E51: -9.25 | F51: =D51+E51 -> 7.65
A52: CIBIL 750-774 | B52: =$B$14 -> 16.9 | D52: =B52+C52 -> 16.9 | E52: -9.15 | F52: =D52+E52 -> 7.75
A53: CIBIL 725-749 | B53: =$B$14 -> 16.9 | D53: =B53+C53 -> 16.9 | E53: -8.95 | F53: =D53+E53 -> 7.95
A54: CIBIL 700-724 | B54: =$B$14 -> 16.9 | D54: =B54+C54 -> 16.9 | E54: -8.65 | F54: =D54+E54 -> 8.25
A55: CIBIL 600-699 | B55: =$B$14 -> 16.9 | D55: =B55+C55 -> 16.9 | E55: -7.4 | F55: =D55+E55 -> 9.5
A57: Condition
A58: Loan amount | B58: More than 2 crs & up to 5 crs
A59: CIBIL <600 | B59: =$B$14 -> 16.9 | D59: =B59+C59 -> 16.9 | E59: -6.9 | F59: =D59+E59 -> 10
A61: Condition
A62: Loan amount | B62: Up to 35 lakhs
A63: 150 ≤ CIBIL ≤ 200 | B63: =$B$14 -> 16.9 | D63: =B63+C63 -> 16.9 | E63: -9.25 | F63: =D63+E63 -> 7.65
A64: 101 ≤ CIBIL < 150 | B64: =$B$14 -> 16.9 | D64: =B64+C64 -> 16.9 | E64: -8.95 | F64: =D64+E64 -> 7.95
A66: Condition
A67: Loan amount | B67: More than 35 lakhs & up to 2 crs
A68: 150 ≤ CIBIL ≤ 200 | B68: =$B$14 -> 16.9 | D68: =B68+C68 -> 16.9 | E68: -9.15 | F68: =D68+E68 -> 7.75
A69: 101 ≤ CIBIL < 150 | B69: =$B$14 -> 16.9 | D69: =B69+C69 -> 16.9 | E69: -8.85 | F69: =D69+E69 -> 8.05
A71: Occupation | B71: Self-Employed
A72: Scheme | B72: Home Loan
A73: Loan type | B73: Term loan
A74: Floating rate
B75: Repo Rate | D75: Rate base | E75: Discount / Extra | F75: Final rate
A76: Condition
A77: Loan amount | B77: Up to 5 crs
A78: CIBIL ≥ 825 | B78: =$B$14 -> 16.9 | D78: =B78+C78 -> 16.9 | E78: -9.65 | F78: =D78+E78 -> 7.25
A79: CIBIL 800-824 | B79: =$B$14 -> 16.9 | D79: =B79+C79 -> 16.9 | E79: -9.55 | F79: =D79+E79 -> 7.35
A81: Condition
A82: Loan amount | B82: More than 5 crs & up to 15 crs
A83: CIBIL ≥ 825 | B83: =$B$14 -> 16.9 | D83: =B83+C83 -> 16.9 | E83: -9.35 | F83: =D83+E83 -> 7.55
A84: CIBIL 800-824 | B84: =$B$14 -> 16.9 | D84: =B84+C84 -> 16.9 | E84: -9.25 | F84: =D84+E84 -> 7.65
A86: Condition
A87: Loan amount | B87: Up to 50 lakhs
A88: CIBIL 775-799 | B88: =$B$14 -> 16.9 | D88: =B88+C88 -> 16.9 | E88: -9.45 | F88: =D88+E88 -> 7.45
A89: CIBIL 750-774 | B89: =$B$14 -> 16.9 | D89: =B89+C89 -> 16.9 | E89: -9.35 | F89: =D89+E89 -> 7.55
A90: CIBIL 725-749 | B90: =$B$14 -> 16.9 | D90: =B90+C90 -> 16.9 | E90: -9.15 | F90: =D90+E90 -> 7.75
A91: CIBIL 700-724 | B91: =$B$14 -> 16.9 | D91: =B91+C91 -> 16.9 | E91: -8.75 | F91: =D91+E91 -> 8.15
A92: CIBIL 600-699 | B92: =$B$14 -> 16.9 | D92: =B92+C92 -> 16.9 | E92: -7.95 | F92: =D92+E92 -> 8.95
A93: CIBIL <600 | B93: =$B$14 -> 16.9 | D93: =B93+C93 -> 16.9 | E93: -7.25 | F93: =D93+E93 -> 9.65
A95: Condition
A96: Loan amount | B96: More than 50 lakhs & up to 2 crs
A97: CIBIL 775-799 | B97: =$B$14 -> 16.9 | D97: =B97+C97 -> 16.9 | E97: -9.35 | F97: =D97+E97 -> 7.55
A98: CIBIL 750-774 | B98: =$B$14 -> 16.9 | D98: =B98+C98 -> 16.9 | E98: -9.25 | F98: =D98+E98 -> 7.65
A99: CIBIL 725-749 | B99: =$B$14 -> 16.9 | D99: =B99+C99 -> 16.9 | E99: -9.05 | F99: =D99+E99 -> 7.85
A100: CIBIL 700-724 | B100: =$B$14 -> 16.9 | D100: =B100+C100 -> 16.9 | E100: -8.65 | F100: =D100+E100 -> 8.25
A101: CIBIL 600-699 | B101: =$B$14 -> 16.9 | D101: =B101+C101 -> 16.9 | E101: -7.85 | F101: =D101+E101 -> 9.05
A102: CIBIL <600 | B102: =$B$14 -> 16.9 | D102: =B102+C102 -> 16.9 | E102: -7.15 | F102: =D102+E102 -> 9.75
A104: Condition
A105: Loan amount | B105: More than 2 crs & up to 15 crs
A106: CIBIL 775-799 | B106: =$B$14 -> 16.9 | D106: =B106+C106 -> 16.9 | E106: -9.15 | F106: =D106+E106 -> 7.75
A107: CIBIL 750-774 | B107: =$B$14 -> 16.9 | D107: =B107+C107 -> 16.9 | E107: -9.05 | F107: =D107+E107 -> 7.85
A108: CIBIL 725-749 | B108: =$B$14 -> 16.9 | D108: =B108+C108 -> 16.9 | E108: -8.85 | F108: =D108+E108 -> 8.05
A109: CIBIL 700-724 | B109: =$B$14 -> 16.9 | D109: =B109+C109 -> 16.9 | E109: -8.45 | F109: =D109+E109 -> 8.45
A110: CIBIL 600-699 | B110: =$B$14 -> 16.9 | D110: =B110+C110 -> 16.9 | E110: -7.3 | F110: =D110+E110 -> 9.6
A112: Condition
A113: Loan amount | B113: More than 2 crs & up to 5 crs
A114: CIBIL <600 | B114: =$B$14 -> 16.9 | D114: =B114+C114 -> 16.9 | E114: -6.8 | F114: =D114+E114 -> 10.1
...

Sheet PNB Housing Finance
A1: Bank | B1: PNB Housing Finance
A2: Interest rate link | B2: https://www.pnbhousing.com/home-loan/interest-rates#pnbTabs
A3: Credit score range given | B3: Yes
A4: Interest rates as per score | B4: Yes
A5: Gender split | B5: No
A6: Occupation split | B6: Yes
A7: Rate types | B7: Floating & Fixed
A8: Rate base | B8: Published rate (CIBIL & loan slab linked)
A9: Special Govt. Employees | B9: No
A10: Loan Type - Term Loan | B10: Yes
A11: Loan Type - Overdraft | B11: No
A12: Top up | B12: No
... A14: Fixed rate | B14: 14.75% (fixed rate for home loan)
A15: PNB Housing Finance Reference Rate | B15: 13.5
A16: Occupation | B16: Salaried
A17: Scheme | B17: Home Loan
A18: Loan type | B18: Term loan
A19: Floating rate
B20: PNB Housing Finance Reference Rate | C20: Markup | D20: Rate base | E20: Discount / Extra | F20: Final rate
A21: Condition
A22: Loan amount | B22: Up to 50 lakhs
A23: NTC CIBIL ≤ 170 | B23: =$B$15 -> 13.5 | D23: =B23+C23 -> 13.5 | E23: -3.85 | F23: =D23+E23 -> 9.65
A24: NTC CIBIL > 170 | B24: =$B$15 -> 13.5 | D24: =B24+C24 -> 13.5 | E24: -3.95 | F24: =D24+E24 -> 9.55
A25: Up to 650 | B25: =$B$15 -> 13.5 | D25: =B25+C25 -> 13.5 | E25: -3.75 | F25: =D25+E25 -> 9.75
A26: > 650 to ≤ 700 | B26: =$B$15 -> 13.5 | D26: =B26+C26 -> 13.5 | E26: -3.75 | F26: =D26+E26 -> 9.75
A27: > 700 to ≤ 725 | B27: =$B$15 -> 13.5 | D27: =B27+C27 -> 13.5 | E27: -4.4 | F27: =D27+E27 -> 9.1
A28: > 725 to ≤ 750 | B28: =$B$15 -> 13.5 | D28: =B28+C28 -> 13.5 | E28: -4.75 | F28: =D28+E28 -> 8.75
A29: > 750 to ≤ 775 | B29: =$B$15 -> 13.5 | D29: =B29+C29 -> 13.5 | E29: -4.9 | F29: =D29+E29 -> 8.6
A30: > 775 to 799 | B30: =$B$15 -> 13.5 | D30: =B30+C30 -> 13.5 | E30: -5 | F30: =D30+E30 -> 8.5
A31: ≥ 800 to 825 | B31: =$B$15 -> 13.5 | D31: =B31+C31 -> 13.5 | E31: -5.1 | F31: =D31+E31 -> 8.4
A32: ≥ 825 | B32: =$B$15 -> 13.5 | D32: =B32+C32 -> 13.5 | E32: -5.75 | F32: =D32+E32 -> 7.75
A34: Condition
A35: Loan amount | B35: 50 lakhs to 1 crore
A36: NTC CIBIL ≤ 170 | B36: =$B$15 -> 13.5 | D36: =B36+C36 -> 13.5 | E36: -3.95 | F36: =D36+E36 -> 9.55
A37: NTC CIBIL > 170 | B37: =$B$15 -> 13.5 | D37: =B37+C37 -> 13.5 | E37: -4.05 | F37: =D37+E37 -> 9.45
A38: Up to 650 | B38: =$B$15 -> 13.5 | D38: =B38+C38 -> 13.5 | E38: -3.85 | F38: =D38+E38 -> 9.65
A39: > 650 to ≤ 700 | B39: =$B$15 -> 13.5 | D39: =B39+C39 -> 13.5 | E39: -3.85 | F39: =D39+E39 -> 9.65
A40: > 700 to ≤ 725 | B40: =$B$15 -> 13.5 | D40: =B40+C40 -> 13.5 | E40: -4.5 | F40: =D40+E40 -> 9
A41: > 725 to ≤ 750 | B41: =$B$15 -> 13.5 | D41: =B41+C41 -> 13.5 | E41: -4.85 | F41: =D41+E41 -> 8.65
A42: > 750 to ≤ 775 | B42: =$B$15 -> 13.5 | D42: =B42+C42 -> 13.5 | E42: -5 | F42: =D42+E42 -> 8.5
A43: > 775 to 799 | B43: =$B$15 -> 13.5 | D43: =B43+C43 -> 13.5 | E43: -5.1 | F43: =D43+E43 -> 8.4
A44: ≥ 800 to 825 | B44: =$B$15 -> 13.5 | D44: =B44+C44 -> 13.5 | E44: -5.2 | F44: =D44+E44 -> 8.3
A45: ≥ 825 | B45: =$B$15 -> 13.5 | D45: =B45+C45 -> 13.5 | E45: -5.9 | F45: =D45+E45 -> 7.6
A47: Condition
A48: Loan amount | B48: Above 1 crore
A49: NTC CIBIL ≤ 170 | B49: =$B$15 -> 13.5 | D49: =B49+C49 -> 13.5 | E49: -4.05 | F49: =D49+E49 -> 9.45
A50: NTC CIBIL > 170 | B50: =$B$15 -> 13.5 | D50: =B50+C50 -> 13.5 | E50: -4.15 | F50: =D50+E50 -> 9.35
A51: Up to 650 | B51: =$B$15 -> 13.5 | D51: =B51+C51 -> 13.5 | E51: -3.95 | F51: =D51+E51 -> 9.55
A52: > 650 to ≤ 700 | B52: =$B$15 -> 13.5 | D52: =B52+C52 -> 13.5 | E52: -3.95 | F52: =D52+E52 -> 9.55
A53: > 700 to ≤ 725 | B53: =$B$15 -> 13.5 | D53: =B53+C53 -> 13.5 | E53: -4.6 | F53: =D53+E53 -> 8.9
A54: > 725 to ≤ 750 | B54: =$B$15 -> 13.5 | D54: =B54+C54 -> 13.5 | E54: -4.95 | F54: =D54+E54 -> 8.55
A55: > 750 to ≤ 775 | B55: =$B$15 -> 13.5 | D55: =B55+C55 -> 13.5 | E55: -5.1 | F55: =D55+E55 -> 8.4
A56: > 775 to 799 | B56: =$B$15 -> 13.5 | D56: =B56+C56 -> 13.5 | E56: -5.2 | F56: =D56+E56 -> 8.3
A57: ≥ 800 to 825 | B57: =$B$15 -> 13.5 | D57: =B57+C57 -> 13.5 | E57: -5.3 | F57: =D57+E57 -> 8.2
A58: ≥ 825 | B58: =$B$15 -> 13.5 | D58: =B58+C58 -> 13.5 | E58: -6 | F58: =D58+E58 -> 7.5
A61: Occupation | B61: Non-Salaried
A62: Scheme | B62: Home Loan
A63: Loan type | B63: Term loan
A64: Floating rate
B65: Repo Rate | C65: Markup | D65: Rate base | E65: Discount / Extra | F65: Final rate
A66: Condition
A67: Loan amount | B67: Up to 50 lakhs
A68: NTC CIBIL ≤ 170 | B68: =$B$15 -> 13.5 | D68: =B68+C68 -> 13.5 | E68: -3.55 | F68: =D68+E68 -> 9.95
A69: NTC CIBIL > 170 | B69: =$B$15 -> 13.5 | D69: =B69+C69 -> 13.5 | E69: -3.65 | F69: =D69+E69 -> 9.85
A70: Up to 650 | B70: =$B$15 -> 13.5 | D70: =B70+C70 -> 13.5 | E70: -3.45 | F70: =D70+E70 -> 10.05
A71: > 650 to ≤ 700 | B71: =$B$15 -> 13.5 | D71: =B71+C71 -> 13.5 | E71: -3.45 | F71: =D71+E71 -> 10.05
A72: > 700 to ≤ 725 | B72: =$B$15 -> 13.5 | D72: =B72+C72 -> 13.5 | E72: -4.1 | F72: =D72+E72 -> 9.4
A73: > 725 to ≤ 750 | B73: =$B$15 -> 13.5 | D73: =B73+C73 -> 13.5 | E73: -4.45 | F73: =D73+E73 -> 9.05
A74: > 750 to ≤ 775 | B74: =$B$15 -> 13.5 | D74: =B74+C74 -> 13.5 | E74: -4.6 | F74: =D74+E74 -> 8.9
A75: > 775 to 799 | B75: =$B$15 -> 13.5 | D75: =B75+C75 -> 13.5 | E75: -4.7 | F75: =D75+E75 -> 8.8
A76: ≥ 800 to 825 | B76: =$B$15 -> 13.5 | D76: =B76+C76 -> 13.5 | E76: -4.8 | F76: =D76+E76 -> 8.7
A77: ≥ 825 | B77: =$B$15 -> 13.5 | D77: =B77+C77 -> 13.5 | E77: -5.5 | F77: =D77+E77 -> 8
A79: Condition
A80: Loan amount | B80: 50 lakhs to 1 crore
A81: NTC CIBIL ≤ 170 | B81: =$B$15 -> 13.5 | D81: =B81+C81 -> 13.5 | E81: -3.65 | F81: =D81+E81 -> 9.85
A82: NTC CIBIL > 170 | B82: =$B$15 -> 13.5 | D82: =B82+C82 -> 13.5 | E82: -3.75 | F82: =D82+E82 -> 9.75
A83: Up to 650 | B83: =$B$15 -> 13.5 | D83: =B83+C83 -> 13.5 | E83: -3.55 | F83: =D83+E83 -> 9.95
A84: > 650 to ≤ 700 | B84: =$B$15 -> 13.5 | D84: =B84+C84 -> 13.5 | E84: -3.55 | F84: =D84+E84 -> 9.95
A85: > 700 to ≤ 725 | B85: =$B$15 -> 13.5 | D85: =B85+C85 -> 13.5 | E85: -4.2 | F85: =D85+E85 -> 9.3
A86: > 725 to ≤ 750 | B86: =$B$15 -> 13.5 | D86: =B86+C86 -> 13.5 | E86: -4.55 | F86: =D86+E86 -> 8.95
A87: > 750 to ≤ 775 | B87: =$B$15 -> 13.5 | D87: =B87+C87 -> 13.5 | E87: -4.7 | F87: =D87+E87 -> 8.8
A88: > 775 to 799 | B88: =$B$15 -> 13.5 | D88: =B88+C88 -> 13.5 | E88: -4.8 | F88: =D88+E88 -> 8.7
A89: ≥ 800 to 825 | B89: =$B$15 -> 13.5 | D89: =B89+C89 -> 13.5 | E89: -4.9 | F89: =D89+E89 -> 8.6
A90: ≥ 825 | B90: =$B$15 -> 13.5 | D90: =B90+C90 -> 13.5 | E90: -5.65 | F90: =D90+E90 -> 7.85
A92: Condition
A93: Loan amount | B93: Above 1 crore
A94: NTC CIBIL ≤ 170 | B94: =$B$15 -> 13.5 | D94: =B94+C94 -> 13.5 | E94: -3.75 | F94: =D94+E94 -> 9.75
A95: NTC CIBIL > 170 | B95: =$B$15 -> 13.5 | D95: =B95+C95 -> 13.5 | E95: -3.85 | F95: =D95+E95 -> 9.65
A96: Up to 650 | B96: =$B$15 -> 13.5 | D96: =B96+C96 -> 13.5 | E96: -3.65 | F96: =D96+E96 -> 9.85
A97: > 650 to ≤ 700 | B97: =$B$15 -> 13.5 | D97: =B97+C97 -> 13.5 | E97: -3.65 | F97: =D97+E97 -> 9.85
A98: > 700 to ≤ 725 | B98: =$B$15 -> 13.5 | D98: =B98+C98 -> 13.5 | E98: -4.3 | F98: =D98+E98 -> 9.2
A99: > 725 to ≤ 750 | B99: =$B$15 -> 13.5 | D99: =B99+C99 -> 13.5 | E99: -4.65 | F99: =D99+E99 -> 8.85
A100: > 750 to ≤ 775 | B100: =$B$15 -> 13.5 | D100: =B100+C100 -> 13.5 | E100: -4.8 | F100: =D100+E100 -> 8.7
A101: > 775 to 799 | B101: =$B$15 -> 13.5 | D101: =B101+C101 -> 13.5 | E101: -4.9 | F101: =D101+E101 -> 8.6
A102: ≥ 800 to 825 | B102: =$B$15 -> 13.5 | D102: =B102+C102 -> 13.5 | E102: -5 | F102: =D102+E102 -> 8.5
A103: ≥ 825 | B103: =$B$15 -> 13.5 | D103: =B103+C103 -> 13.5 | E103: -5.75 | F103: =D103+E103 -> 7.75

Sheet Sheet1
